Workbook

Sheet Assumptions
B2: Netflix | E2: SCENARIO SELECTION -> | G2: =+Valuation!M2 -> 1 | H2: Función | I2: Offset
B3: Model Assumptions | G3: =IF(G2=1,"Base Case", IF(G2=2,"Bull Case", IF(G2=3,"Bear Case","-"))) -> Base Case | I3: Desref
B5: Assumptions Netflix | D5: FY2021 | E5: FY2022 | F5: FY2023 | G5: FY2024 | H5: FY2025 | I5: FY2026 | J5: FY2027
B7: Revenues United Estates & Canada | D7: =OFFSET(D7,$G$2,,,) -> 12972100 | E7: {=OFFSET(E7,$G$2,,,)} -> 13893119 | F7: {=OFFSET(F7,$G$2,,,)} -> 14879531 | G7: =OFFSET(G7,$G$2,,,) -> 15935977 | H7: =OFFSET(H7,$G$2,,,) -> 17067432 | I7: =OFFSET(I7,$G$2,,,) -> 18279219 | J7: =OFFSET(J7,$G$2,,,) -> 19577044
B8: Base Case | D8: 12972100 | E8: =+E13*E23 -> 13893119 | F8: =+F13*F23 -> 14879531 | G8: =+G13*G23 -> 15935977 | H8: =+H13*H23 -> 17067432 | I8: =+I13*I23 -> 18279219 | J8: =+J13*J23 -> 19577044
B9: Bull Case | D9: 12972100 | E9: =+E14*E24 -> 14162939 | F9: =+F14*F24 -> 15463097 | G9: =+G14*G24 -> 16882609 | H9: =+H14*H24 -> 18432432 | I9: =+I14*I24 -> 20124530 | J9: =+J14*J24 -> 21971961
B10: Bear Case | D10: 12972100 | E10: =+E15*E25 -> 13363857 | F10: =+F15*F25 -> 13767446 | G10: =+G15*G25 -> 14183223 | H10: =+H15*H25 -> 14611556 | I10: =+I15*I25 -> 15052825 | J10: =+J15*J25 -> 15507420
B12: Paid Mememberships United Estates & Canada | D12: =OFFSET(D12,$G$2,,,) -> 75215 | E12: =OFFSET(E12,$G$2,,,) -> 76719.3 | F12: =OFFSET(F12,$G$2,,,) -> 78253.686 | G12: =OFFSET(G12,$G$2,,,) -> 79818.76 | H12: =OFFSET(H12,$G$2,,,) -> 81415.135 | I12: =OFFSET(I12,$G$2,,,) -> 83043.438 | J12: =OFFSET(J12,$G$2,,,) -> 84704.306
B13: Base Case | D13: 75215 | E13: =+D13*(1+E18) -> 76719.3 | F13: =+E13*(1+F18) -> 78253.686 | G13: =+F13*(1+G18) -> 79818.76 | H13: =+G13*(1+H18) -> 81415.135 | I13: =+H13*(1+I18) -> 83043.438 | J13: =+I13*(1+J18) -> 84704.306
B14: Bull Case | D14: 75215 | E14: =+D14*(1+E19) -> 77471.45 | F14: =+E14*(1+F19) -> 79795.594 | G14: =+F14*(1+G19) -> 82189.461 | H14: =+G14*(1+H19) -> 84655.145 | I14: =+H14*(1+I19) -> 87194.799 | J14: =+I14*(1+J19) -> 89810.643
B15: Bear Case | D15: 75215 | E15: =+D15*(1+E20) -> 75967.15 | F15: =+E15*(1+F20) -> 76726.822 | G15: =+F15*(1+G20) -> 77494.09 | H15: =+G15*(1+H20) -> 78269.031 | I15: =+H15*(1+I20) -> 79051.721 | J15: =+I15*(1+J20) -> 79842.238
B17: Paid Mememberships Growth United Estates & Canada | D17: =OFFSET(D17,$G$2,,,) | E17: =OFFSET(E17,$G$2,,,) -> 0.02 | F17: =OFFSET(F17,$G$2,,,) -> 0.02 | G17: =OFFSET(G17,$G$2,,,) -> 0.02 | H17: =OFFSET(H17,$G$2,,,) -> 0.02 | I17: =OFFSET(I17,$G$2,,,) -> 0.02 | J17: =OFFSET(J17,$G$2,,,) -> 0.02
B18: Base Case | E18: 0.02 | F18: 0.02 | G18: 0.02 | H18: 0.02 | I18: 0.02 | J18: 0.02
B19: Bull Case | E19: 0.03 | F19: 0.03 | G19: 0.03 | H19: 0.03 | I19: 0.03 | J19: 0.03
B20: Bear Case | E20: 0.01 | F20: 0.01 | G20: 0.01 | H20: 0.01 | I20: 0.01 | J20: 0.01
B22: Average Price United Estates & Canada | D22: =OFFSET(D22,$G$2,,,) -> 172.46693 | E22: =OFFSET(E22,$G$2,,,) -> 181.09027 | F22: =OFFSET(F22,$G$2,,,) -> 190.14479 | G22: =OFFSET(G22,$G$2,,,) -> 199.65203 | H22: =OFFSET(H22,$G$2,,,) -> 209.63463 | I22: =OFFSET(I22,$G$2,,,) -> 220.11636 | J22: =OFFSET(J22,$G$2,,,) -> 231.12218
B23: Base Case | D23: =+D8/D13 -> 172.46693 | E23: =+D23*(1+E28) -> 181.09027 | F23: =+E23*(1+F28) -> 190.14479 | G23: =+F23*(1+G28) -> 199.65203 | H23: =+G23*(1+H28) -> 209.63463 | I23: =+H23*(1+I28) -> 220.11636 | J23: =+I23*(1+J28) -> 231.12218
B24: Bull Case | D24: =+D9/D14 -> 172.46693 | E24: =+D24*(1+E29) -> 182.81494 | F24: =+E24*(1+F29) -> 193.78384 | G24: =+F24*(1+G29) -> 205.41087 | H24: =+G24*(1+H29) -> 217.73552 | I24: =+H24*(1+I29) -> 230.79965 | J24: =+I24*(1+J29) -> 244.64763
B25: Bear Case | D25: =+D10/D15 -> 172.46693 | E25: =+D25*(1+E30) -> 175.91627 | F25: =+E25*(1+F30) -> 179.43459 | G25: =+F25*(1+G30) -> 183.02328 | H25: =+G25*(1+H30) -> 186.68375 | I25: =+H25*(1+I30) -> 190.41742 | J25: =+I25*(1+J30) -> 194.22577
B27: Average Price Growth United Estates & Canada | D27: =OFFSET(D27,$G$2,,,) | E27: =OFFSET(E27,$G$2,,,) -> 0.05 | F27: =OFFSET(F27,$G$2,,,) -> 0.05 | G27: =OFFSET(G27,$G$2,,,) -> 0.05 | H27: =OFFSET(H27,$G$2,,,) -> 0.05 | I27: =OFFSET(I27,$G$2,,,) -> 0.05 | J27: =OFFSET(J27,$G$2,,,) -> 0.05
B28: Base Case | E28: 0.05 | F28: 0.05 | G28: 0.05 | H28: 0.05 | I28: 0.05 | J28: 0.05
B29: Bull Case | E29: 0.06 | F29: 0.06 | G29: 0.06 | H29: 0.06 | I29: 0.06 | J29: 0.06
B30: Bear Case | E30: 0.02 | F30: 0.02 | G30: 0.02 | H30: 0.02 | I30: 0.02 | J30: 0.02
B32: Revenues EMEA | D32: =OFFSET(D32,$G$2,,,) -> 9699819 | E32: =OFFSET(E32,$G$2,,,) -> 10541278 | F32: =OFFSET(F32,$G$2,,,) -> 11455734 | G32: =OFFSET(G32,$G$2,,,) -> 12449519 | H32: =OFFSET(H32,$G$2,,,) -> 13529515 | I32: =OFFSET(I32,$G$2,,,) -> 14703200 | J32: =OFFSET(J32,$G$2,,,) -> 15978703
B33: Base Case | D33: 9699819 | E33: =+E38*E48 -> 10541278 | F33: =+F38*F48 -> 11455734 | G33: =+G38*G48 -> 12449519 | H33: =+H38*H48 -> 13529515 | I33: =+I38*I48 -> 14703200 | J33: =+J38*J48 -> 15978703
B34: Bull Case | D34: 9699819 | E34: =+E39*E49 -> 10795899 | F34: =+F39*F49 -> 12015835 | G34: =+G39*G49 -> 13373624 | H34: =+H39*H49 -> 14884844 | I34: =+I39*I49 -> 16566831 | J34: =+J39*J49 -> 18438883
B35: Bear Case | D35: 9699819 | E35: =+E40*E50 -> 10240099 | F35: =+F40*F50 -> 10810472 | G35: =+G40*G50 -> 11412616 | H35: =+H40*H50 -> 12048298 | I35: =+I40*I50 -> 12719389 | J35: =+J40*J50 -> 13427859
B37: Paid Mememberships EMEA | D37: =OFFSET(D37,$G$2,,,) -> 74036 | E37: =OFFSET(E37,$G$2,,,) -> 77737.8 | F37: =OFFSET(F37,$G$2,,,) -> 81624.69 | G37: =OFFSET(G37,$G$2,,,) -> 85705.924 | H37: =OFFSET(H37,$G$2,,,) -> 89991.221 | I37: =OFFSET(I37,$G$2,,,) -> 94490.782 | J37: =OFFSET(J37,$G$2,,,) -> 99215.321
B38: Base Case | D38: 74036 | E38: =+D38*(1+E43) -> 77737.8 | F38: =+E38*(1+F43) -> 81624.69 | G38: =+F38*(1+G43) -> 85705.924 | H38: =+G38*(1+H43) -> 89991.221 | I38: =+H38*(1+I43) -> 94490.782 | J38: =+I38*(1+J43) -> 99215.321
B39: Bull Case | D39: 74036 | E39: =+D39*(1+E44) -> 78478.16 | F39: =+E39*(1+F44) -> 83186.85 | G39: =+F39*(1+G44) -> 88178.061 | H39: =+G39*(1+H44) -> 93468.744 | I39: =+H39*(1+I44) -> 99076.869 | J39: =+I39*(1+J44) -> 105021.48
B40: Bear Case | D40: 74036 | E40: =+D40*(1+E45) -> 76627.26 | F40: =+E40*(1+F45) -> 79309.214 | G40: =+F40*(1+G45) -> 82085.037 | H40: =+G40*(1+H45) -> 84958.013 | I40: =+H40*(1+I45) -> 87931.543 | J40: =+I40*(1+J45) -> 91009.147
B42: Paid Mememberships Growth EMEA | D42: =OFFSET(D42,$G$2,,,) | E42: =OFFSET(E42,$G$2,,,) -> 0.05 | F42: =OFFSET(F42,$G$2,,,) -> 0.05 | G42: =OFFSET(G42,$G$2,,,) -> 0.05 | H42: =OFFSET(H42,$G$2,,,) -> 0.05 | I42: =OFFSET(I42,$G$2,,,) -> 0.05 | J42: =OFFSET(J42,$G$2,,,) -> 0.05
B43: Base Case | E43: 0.05 | F43: 0.05 | G43: 0.05 | H43: 0.05 | I43: 0.05 | J43: 0.05
B44: Bull Case | E44: 0.06 | F44: 0.06 | G44: 0.06 | H44: 0.06 | I44: 0.06 | J44: 0.06
B45: Bear Case | E45: 0.035 | F45: 0.035 | G45: 0.035 | H45: 0.035 | I45: 0.035 | J45: 0.035
B47: Average Price EMEA | D47: =OFFSET(D47,$G$2,,,) -> 131.0149 | E47: =OFFSET(E47,$G$2,,,) -> 135.60042 | F47: =OFFSET(F47,$G$2,,,) -> 140.34643 | G47: =OFFSET(G47,$G$2,,,) -> 145.25856 | H47: =OFFSET(H47,$G$2,,,) -> 150.34261 | I47: =OFFSET(I47,$G$2,,,) -> 155.6046 | J47: =OFFSET(J47,$G$2,,,) -> 161.05076
B48: Base Case | D48: 131.0149 | E48: =+D48*(1+E53) -> 135.60042 | F48: =+E48*(1+F53) -> 140.34643 | G48: =+F48*(1+G53) -> 145.25856 | H48: =+G48*(1+H53) -> 150.34261 | I48: =+H48*(1+I53) -> 155.6046 | J48: =+I48*(1+J53) -> 161.05076
B49: Bull Case | D49: 131.0149 | E49: =+D49*(1+E54) -> 137.56564 | F49: =+E49*(1+F54) -> 144.44393 | G49: =+F49*(1+G54) -> 151.66612 | H49: =+G49*(1+H54) -> 159.24943 | I49: =+H49*(1+I54) -> 167.2119 | J49: =+I49*(1+J54) -> 175.57249
B50: Bear Case | D50: 131.0149 | E50: =+D50*(1+E55) -> 133.6352 | F50: =+E50*(1+F55) -> 136.3079 | G50: =+F50*(1+G55) -> 139.03406 | H50: =+G50*(1+H55) -> 141.81474 | I50: =+H50*(1+I55) -> 144.65103 | J50: =+I50*(1+J55) -> 147.54405
B52: Average Price Growth EMEA | D52: =OFFSET(D52,$G$2,,,) | E52: =OFFSET(E52,$G$2,,,) -> 0.035 | F52: =OFFSET(F52,$G$2,,,) -> 0.035 | G52: =OFFSET(G52,$G$2,,,) -> 0.035 | H52: =OFFSET(H52,$G$2,,,) -> 0.035 | I52: =OFFSET(I52,$G$2,,,) -> 0.035 | J52: =OFFSET(J52,$G$2,,,) -> 0.035
B53: Base Case | E53: 0.035 | F53: 0.035 | G53: 0.035 | H53: 0.035 | I53: 0.035 | J53: 0.035
B54: Bull Case | E54: 0.05 | F54: 0.05 | G54: 0.05 | H54: 0.05 | I54: 0.05 | J54: 0.05
B55: Bear Case | E55: 0.02 | F55: 0.02 | G55: 0.02 | H55: 0.02 | I55: 0.02 | J55: 0.02
B57: Revenues LATAM | D57: =OFFSET(D57,$G$2,,,) -> 3576976 | E57: =OFFSET(E57,$G$2,,,) -> 3887278.7 | F57: =OFFSET(F57,$G$2,,,) -> 4224500.1 | G57: =OFFSET(G57,$G$2,,,) -> 4590975.5 | H57: =OFFSET(H57,$G$2,,,) -> 4989242.6 | I57: =OFFSET(I57,$G$2,,,) -> 5422059.4 | J57: =OFFSET(J57,$G$2,,,) -> 5892423
B58: Base Case | D58: 3576976 | E58: =+E63*E73 -> 3887278.7 | F58: =+F63*F73 -> 4224500.1 | G58: =+G63*G73 -> 4590975.5 | H58: =+H63*H73 -> 4989242.6 | I58: =+I63*I73 -> 5422059.4 | J58: =+J63*J73 -> 5892423
B59: Bull Case | D59: 3576976 | E59: =+E64*E74 -> 3943258.3 | F59: =+F64*F74 -> 4347048 | G59: =+G64*G74 -> 4792185.7 | H59: =+H64*H74 -> 5282905.5 | I59: =+I64*I74 -> 5823875.1 | J59: =+J64*J74 -> 6420239.9
B60: Bear Case | D60: 3576976 | E60: =+E65*E75 -> 3757971 | F60: =+F65*F75 -> 3948124.3 | G60: =+G65*G75 -> 4147899.4 | H60: =+H65*H75 -> 4357783.1 | I60: =+I65*I75 -> 4578286.9 | J60: =+J65*J75 -> 4809948.3
B62: Paid Mememberships LATAM | D62: =OFFSET(D62,$G$2,,,) -> 39961 | E62: =OFFSET(E62,$G$2,,,) -> 41959.05 | F62: =OFFSET(F62,$G$2,,,) -> 44057.003 | G62: =OFFSET(G62,$G$2,,,) -> 46259.853 | H62: =OFFSET(H62,$G$2,,,) -> 48572.845 | I62: =OFFSET(I62,$G$2,,,) -> 51001.488 | J62: =OFFSET(J62,$G$2,,,) -> 53551.562
B63: Base Case | D63: 39961 | E63: =+D63*(1+E68) -> 41959.05 | F63: =+E63*(1+F68) -> 44057.003 | G63: =+F63*(1+G68) -> 46259.853 | H63: =+G63*(1+H68) -> 48572.845 | I63: =+H63*(1+I68) -> 51001.488 | J63: =+I63*(1+J68) -> 53551.562
B64: Bull Case | D64: 39961 | E64: =+D64*(1+E69) -> 42358.66 | F64: =+E64*(1+F69) -> 44900.18 | G64: =+F64*(1+G69) -> 47594.19 | H64: =+G64*(1+H69) -> 50449.842 | I64: =+H64*(1+I69) -> 53476.832 | J64: =+I64*(1+J69) -> 56685.442
B65: Bear Case | D65: 39961 | E65: =+D65*(1+E70) -> 41159.83 | F65: =+E65*(1+F70) -> 42394.625 | G65: =+F65*(1+G70) -> 43666.464 | H65: =+G65*(1+H70) -> 44976.458 | I65: =+H65*(1+I70) -> 46325.751 | J65: =+I65*(1+J70) -> 47715.524
B67: Paid Mememberships Growth LATAM | D67: =OFFSET(D67,$G$2,,,) | E67: =OFFSET(E67,$G$2,,,) -> 0.05 | F67: =OFFSET(F67,$G$2,,,) -> 0.05 | G67: =OFFSET(G67,$G$2,,,) -> 0.05 | H67: =OFFSET(H67,$G$2,,,) -> 0.05 | I67: =OFFSET(I67,$G$2,,,) -> 0.05 | J67: =OFFSET(J67,$G$2,,,) -> 0.05
B68: Base Case | E68: 0.05 | F68: 0.05 | G68: 0.05 | H68: 0.05 | I68: 0.05 | J68: 0.05
B69: Bull Case | E69: 0.06 | F69: 0.06 | G69: 0.06 | H69: 0.06 | I69: 0.06 | J69: 0.06
B70: Bear Case | E70: 0.03 | F70: 0.03 | G70: 0.03 | H70: 0.03 | I70: 0.03 | J70: 0.03
B72: Average Price LATAM | D72: =OFFSET(D72,$G$2,,,) -> 89.511674 | E72: =OFFSET(E72,$G$2,,,) -> 92.644582 | F72: =OFFSET(F72,$G$2,,,) -> 95.887143 | G72: =OFFSET(G72,$G$2,,,) -> 99.243193 | H72: =OFFSET(H72,$G$2,,,) -> 102.7167 | I72: =OFFSET(I72,$G$2,,,) -> 106.31179 | J72: =OFFSET(J72,$G$2,,,) -> 110.0327
B73: Base Case | D73: 89.511674 | E73: =+D73*(1+E78) -> 92.644582 | F73: =+E73*(1+F78) -> 95.887143 | G73: =+F73*(1+G78) -> 99.243193 | H73: =+G73*(1+H78) -> 102.7167 | I73: =+H73*(1+I78) -> 106.31179 | J73: =+I73*(1+J78) -> 110.0327
B74: Bull Case | D74: 89.511674 | E74: =+D74*(1+E79) -> 93.092141 | F74: =+E74*(1+F79) -> 96.815826 | G74: =+F74*(1+G79) -> 100.68846 | H74: =+G74*(1+H79) -> 104.716 | I74: =+H74*(1+I79) -> 108.90464 | J74: =+I74*(1+J79) -> 113.26082
B75: Bear Case | D75: 89.511674 | E75: =+D75*(1+E80) -> 91.301907 | F75: =+E75*(1+F80) -> 93.127946 | G75: =+F75*(1+G80) -> 94.990504 | H75: =+G75*(1+H80) -> 96.890315 | I75: =+H75*(1+I80) -> 98.828121 | J75: =+I75*(1+J80) -> 100.80468
B77: Average Price Growth LATAM | D77: =OFFSET(D77,$G$2,,,) | E77: =OFFSET(E77,$G$2,,,) -> 0.035 | F77: =OFFSET(F77,$G$2,,,) -> 0.035 | G77: =OFFSET(G77,$G$2,,,) -> 0.035 | H77: =OFFSET(H77,$G$2,,,) -> 0.035 | I77: =OFFSET(I77,$G$2,,,) -> 0.035 | J77: =OFFSET(J77,$G$2,,,) -> 0.035
B78: Base Case | E78: 0.035 | F78: 0.035 | G78: 0.035 | H78: 0.035 | I78: 0.035 | J78: 0.035
B79: Bull Case | E79: 0.04 | F79: 0.04 | G79: 0.04 | H79: 0.04 | I79: 0.04 | J79: 0.04
B80: Bear Case | E80: 0.02 | F80: 0.02 | G80: 0.02 | H80: 0.02 | I80: 0.02 | J80: 0.02
B82: Revenues Asia-Pacific | D82: =OFFSET(D82,$G$2,,,) -> 3266601 | E82: =OFFSET(E82,$G$2,,,) -> 3944420.7 | F82: =OFFSET(F82,$G$2,,,) -> 4717527.2 | G82: =OFFSET(G82,$G$2,,,) -> 5223482 | H82: =OFFSET(H82,$G$2,,,) -> 5649195.7 | I82: =OFFSET(I82,$G$2,,,) -> 5964138.4 | J82: =OFFSET(J82,$G$2,,,) -> 6296639.1
B83: Base Case | D83: 3266601 | E83: =+E88*E98 -> 3944420.7 | F83: =+F88*F98 -> 4717527.2 | G83: =+G88*G98 -> 5223482 | H83: =+H88*H98 -> 5649195.7 | I83: =+I88*I98 -> 5964138.4 | J83: =+J88*J98 -> 6296639.1
B84: Bull Case | D84: 3266601 | E84: =+E89*E99 -> 4155116.5 | F84: =+F89*F99 -> 5235446.8 | G84: =+G89*G99 -> 5989351.1 | H84: =+H89*H99 -> 6696094.5 | I84: =+I89*I99 -> 7312135.2 | J84: =+J89*J99 -> 7832759.2
B85: Bear Case | D85: 3266601 | E85: =+E90*E100 -> 3736991.5 | F85: =+F90*F100 -> 4234011.4 | G85: =+G90*G100 -> 4579083.3 | H85: =+H90*H100 -> 4834367.2 | I85: =+I90*I100 -> 5078986.2 | J85: =+J90*J100 -> 5335982.9
B87: Paid Mememberships Asia-Pacific | D87: =OFFSET(D87,$G$2,,,) -> 32632 | E87: =OFFSET(E87,$G$2,,,) -> 37526.8 | F87: =OFFSET(F87,$G$2,,,) -> 43155.82 | G87: =OFFSET(G87,$G$2,,,) -> 46392.507 | H87: =OFFSET(H87,$G$2,,,) -> 48712.132 | I87: =OFFSET(I87,$G$2,,,) -> 49929.935 | J87: =OFFSET(J87,$G$2,,,) -> 51178.183
B88: Base Case | D88: 32632 | E88: =+D88*(1+E93) -> 37526.8 | F88: =+E88*(1+F93) -> 43155.82 | G88: =+F88*(1+G93) -> 46392.507 | H88: =+G88*(1+H93) -> 48712.132 | I88: =+H88*(1+I93) -> 49929.935 | J88: =+I88*(1+J93) -> 51178.183
B89: Bull Case | D89: 32632 | E89: =+D89*(1+E94) -> 39158.4 | F89: =+E89*(1+F94) -> 46990.08 | G89: =+F89*(1+G94) -> 51689.088 | H89: =+G89*(1+H94) -> 55565.77 | I89: =+H89*(1+I94) -> 58344.058 | J89: =+I89*(1+J94) -> 60094.38
B90: Bear Case | D90: 32632 | E90: =+D90*(1+E95) -> 35895.2 | F90: =+E90*(1+F95) -> 39484.72 | G90: =+F90*(1+G95) -> 41458.956 | H90: =+G90*(1+H95) -> 42495.43 | I90: =+H90*(1+I95) -> 43345.338 | J90: =+I90*(1+J95) -> 44212.245
B92: Paid Mememberships Growth Asia-Pacific | D92: =OFFSET(D92,$G$2,,,) | E92: =OFFSET(E92,$G$2,,,) -> 0.15 | F92: =OFFSET(F92,$G$2,,,) -> 0.15 | G92: =OFFSET(G92,$G$2,,,) -> 0.075 | H92: =OFFSET(H92,$G$2,,,) -> 0.05 | I92: =OFFSET(I92,$G$2,,,) -> 0.025 | J92: =OFFSET(J92,$G$2,,,) -> 0.025
B93: Base Case | E93: 0.15 | F93: 0.15 | G93: 0.075 | H93: 0.05 | I93: 0.025 | J93: 0.025
B94: Bull Case | E94: 0.2 | F94: 0.2 | G94: 0.1 | H94: 0.075 | I94: 0.05 | J94: 0.03
B95: Bear Case | E95: 0.1 | F95: 0.1 | G95: 0.05 | H95: 0.025 | I95: 0.02 | J95: 0.02
B97: Average Price Asia-Pacific | D97: =OFFSET(D97,$G$2,,,) -> 100.10422 | E97: =OFFSET(E97,$G$2,,,) -> 105.10943 | F97: =OFFSET(F97,$G$2,,,) -> 109.31381 | G97: =OFFSET(G97,$G$2,,,) -> 112.59323 | H97: =OFFSET(H97,$G$2,,,) -> 115.97102 | I97: =OFFSET(I97,$G$2,,,) -> 119.45015 | J97: =OFFSET(J97,$G$2,,,) -> 123.03366
B98: Base Case | D98: 100.10422 | E98: =+D98*(1+E103) -> 105.10943 | F98: =+E98*(1+F103) -> 109.31381 | G98: =+F98*(1+G103) -> 112.59323 | H98: =+G98*(1+H103) -> 115.97102 | I98: =+H98*(1+I103) -> 119.45015 | J98: =+I98*(1+J103) -> 123.03366
B99: Bull Case | D99: 100.10422 | E99: =+D99*(1+E104) -> 106.11048 | F99: =+E99*(1+F104) -> 111.416 | G99: =+F99*(1+G104) -> 115.87264 | H99: =+G99*(1+H104) -> 120.50755 | I99: =+H99*(1+I104) -> 125.32785 | J99: =+I99*(1+J104) -> 130.34096
B100: Bear Case | D100: 100.10422 | E100: =+D100*(1+E105) -> 104.10839 | F100: =+E100*(1+F105) -> 107.23164 | G100: =+F100*(1+G105) -> 110.44859 | H100: =+G100*(1+H105) -> 113.76205 | I100: =+H100*(1+I105) -> 117.17491 | J100: =+I100*(1+J105) -> 120.69016
B102: Average Price Growth Asia-Pacific | D102: =OFFSET(D102,$G$2,,,) | E102: =OFFSET(E102,$G$2,,,) -> 0.05 | F102: =OFFSET(F102,$G$2,,,) -> 0.04 | G102: =OFFSET(G102,$G$2,,,) -> 0.03 | H102: =OFFSET(H102,$G$2,,,) -> 0.03 | I102: =OFFSET(I102,$G$2,,,) -> 0.03 | J102: =OFFSET(J102,$G$2,,,) -> 0.03
B103: Base Case | E103: 0.05 | F103: 0.04 | G103: 0.03 | H103: 0.03 | I103: 0.03 | J103: 0.03
B104: Bull Case | E104: 0.06 | F104: 0.05 | G104: 0.04 | H104: 0.04 | I104: 0.04 | J104: 0.04
B105: Bear Case | E105: 0.04 | F105: 0.03 | G105: 0.03 | H105: 0.03 | I105: 0.03 | J105: 0.03
B107: Other Revenues | D107: =OFFSET(D107,$G$2,,,) -> 182348 | E107: =OFFSET(E107,$G$2,,,) -> 136761 | F107: =OFFSET(F107,$G$2,,,) -> 95732.7 | G107: =OFFSET(G107,$G$2,,,) -> 62226.255 | H107: =OFFSET(H107,$G$2,,,) -> 31113.127 | I107: =OFFSET(I107,$G$2,,,) -> 0 | J107: =OFFSET(J107,$G$2,,,) -> 0
B108: Base Case | D108: =+Model!$H$38 -> 182348 | E108: =+D108*(1+E113) -> 136761 | F108: =+E108*(1+F113) -> 95732.7 | G108: =+F108*(1+G113) -> 62226.255 | H108: =+G108*(1+H113) -> 31113.127 | I108: =+H108*(1+I113) -> 0 | J108: =+I108*(1+J113) -> 0
B109: Bull Case | D109: =+Model!$H$38 -> 182348 | E109: =+D109*(1+E114) -> 145878.4 | F109: =+E109*(1+F114) -> 109408.8 | G109: =+F109*(1+G114) -> 65645.28 | H109: =+G109*(1+H114) -> 39387.168 | I109: =+H109*(1+I114) -> 0 | J109: =+I109*(1+J114) -> 0
B110: Bear Case | D110: =+Model!$H$38 -> 182348 | E110: =+D110*(1+E115) -> 127643.6 | F110: =+E110*(1+F115) -> 82968.34 | G110: =+F110*(1+G115) -> 58077.838 | H110: =+G110*(1+H115) -> 23231.135 | I110: =+H110*(1+I115) -> 0 | J110: =+I110*(1+J115) -> 0
B112: Other Revenues Growth | D112: =OFFSET(D112,$G$2,,,) | E112: =OFFSET(E112,$G$2,,,) -> -0.25 | F112: =OFFSET(F112,$G$2,,,) -> -0.3 | G112: =OFFSET(G112,$G$2,,,) -> -0.35 | H112: =OFFSET(H112,$G$2,,,) -> -0.5 | I112: =OFFSET(I112,$G$2,,,) -> -1 | J112: =OFFSET(J112,$G$2,,,) -> -1
B113: Base Case | E113: -0.25 | F113: -0.3 | G113: -0.35 | H113: -0.5 | I113: -1 | J113: -1
B114: Bull Case | E114: -0.2 | F114: -0.25 | G114: -0.4 | H114: -0.4 | I114: -1 | J114: -1
B115: Bear Case | E115: -0.3 | F115: -0.35 | G115: -0.3 | H115: -0.6 | I115: -1 | J115: -1
B117: COGS as % of Revenue | D117: =OFFSET(D117,$G$2,,,) | E117: =OFFSET(E117,$G$2,,,) -> 0.151 | F117: =OFFSET(F117,$G$2,,,) -> 0.151 | G117: =OFFSET(G117,$G$2,,,) -> 0.151 | H117: =OFFSET(H117,$G$2,,,) -> 0.151 | I117: =OFFSET(I117,$G$2,,,) -> 0.151 | J117: =OFFSET(J117,$G$2,,,) -> 0.151
B118: Base Case | E118: 0.151 | F118: 0.151 | G118: 0.151 | H118: 0.151 | I118: 0.151 | J118: 0.151
B119: Bull Case | E119: 0.151 | F119: 0.151 | G119: 0.151 | H119: 0.151 | I119: 0.151 | J119: 0.151
B120: Bear Case | E120: 0.151 | F120: 0.151 | G120: 0.151 | H120: 0.151 | I120: 0.151 | J120: 0.151
B122: Marketing as % of Revenue | D122: =OFFSET(D122,$G$2,,,) | E122: =OFFSET(E122,$G$2,,,) -> 0.08 | F122: =OFFSET(F122,$G$2,,,) -> 0.0775 | G122: =OFFSET(G122,$G$2,,,) -> 0.075 | H122: =OFFSET(H122,$G$2,,,) -> 0.0725 | I122: =OFFSET(I122,$G$2,,,) -> 0.07 | J122: =OFFSET(J122,$G$2,,,) -> 0.07
B123: Base Case | E123: 0.08 | F123: =+E123-0.25% -> 0.0775 | G123: =+F123-0.25% -> 0.075 | H123: =+G123-0.25% -> 0.0725 | I123: =+H123-0.25% -> 0.07 | J123: 0.07
B124: Bull Case | E124: 0.075 | F124: =+E124-0.25% -> 0.0725 | G124: =+F124-0.25% -> 0.07 | H124: =+G124-0.25% -> 0.0675 | I124: =+H124-0.25% -> 0.065 | J124: 0.065
B125: Bear Case | E125: 0.085 | F125: =+E125-0.25% -> 0.0825 | G125: =+F125-0.25% -> 0.08 | H125: =+G125-0.25% -> 0.0775 | I125: =+H125-0.25% -> 0.075 | J125: 0.075
B127: Technology and development as % of Revenue | D127: =OFFSET(D127,$G$2,,,) | E127: =OFFSET(E127,$G$2,,,) -> 0.085 | F127: =OFFSET(F127,$G$2,,,) -> 0.0825 | G127: =OFFSET(G127,$G$2,,,) -> 0.08 | H127: =OFFSET(H127,$G$2,,,) -> 0.08 | I127: =OFFSET(I127,$G$2,,,) -> 0.08 | J127: =OFFSET(J127,$G$2,,,) -> 0.08
...

Sheet Financial Statements
C2: Netflix
C3: Financial Statements
C5: Netflix - in $ thousands | D5: Q1-2022 | E5: Q2-2022 | F5: H1 2022 | G5: Run-rate | H5: Q3-2022 | I5: Q4-2022 | J5: 2022 | K5: Q1-2023 | L5: Q2-2023 | M5: Q3-2023 | N5: Q4-2023 | O5: 2023 | P5: 2024 | Q5: 2025
C6: Revenues | D6: 7867767 | E6: 7970141 | F6: =+E6+D6 -> 15837908 | G6: =+F6*2 -> 31675816
C7: COGS | D7: -4284705 | E7: -4690755 | F7: =+E7+D7 -> -8975460 | G7: =+F7*2 -> -17950920
C8: Gross Profit | D8: =+D7+D6 -> 3583062 | E8: =+E7+E6 -> 3279386 | F8: =+F7+F6 -> 6862448 | G8: =+G7+G6 -> 13724896
C9: Gross Margin | D9: =+D8/D$6 -> 0.45541028 | E9: =+E8/E$6 -> 0.41145897 | F9: =+F8/F$6 -> 0.43329258 | G9: =+G8/G$6 -> 0.43329258
C11: Adjusted COGS | G11: -4779280
C12: Adjusted Gross Profit | G12: =+G11+G73+G74 -> 8392360
C13: Adjusted Gross Margin | G13: 0.84911896
C15: Marketing | D15: -555978 | E15: -574960 | F15: =+E15+D15 -> -1130938 | G15: =+F15*2 -> -2261876
G16: =-G15/G$6 -> 0.071407032
C17: Technology and development | D17: -657530 | E17: -716846 | F17: =+E17+D17 -> -1374376 | G17: =+F17*2 -> -2748752
G18: =-G17/G$6 -> 0.086777622
C19: G&A | D19: -397928 | E19: -409297 | F19: =+E19+D19 -> -807225 | G19: =+F19*2 -> -1614450
G20: =-G19/G$6 -> 0.050967906
C21: EBIT | D21: =+D8+D15+D17+D19 -> 1971626 | E21: =+E8+E15+E17+E19 -> 1578283 | F21: =+F8+F15+F17+F19 -> 3549909 | G21: =+G8+G15+G17+G19 -> 7099818
C22: EBIT Margin | D22: =+D21/D$6 -> 0.25059537 | E22: =+E21/E$6 -> 0.19802448 | F22: =+F21/F$6 -> 0.22414002 | G22: =+G21/G$6 -> 0.22414002
C24: Interest expense | D24: -187579 | E24: -175455 | F24: =+E24+D24 -> -363034 | G24: =+F24*2 -> -726068
C25: Interest and other income | D25: 195645 | E25: 220226 | F25: =+E25+D25 -> 415871 | G25: =+F25*2 -> 831742
C26: Taxes | D26: -382245 | E26: -182103 | F26: =+E26+D26 -> -564348 | G26: =+F26*2 -> -1128696
C27: Net Income | D27: =+D21+D24+D25+D26 -> 1597447 | E27: =+E21+E24+E25+E26 -> 1440951 | F27: =+F21+F24+F25+F26 -> 3038398 | G27: =+G21+G24+G25+G26 -> 6076796
C28: EPS | D28: =+D27/D30 -> 3.5264976 | E28: =+E27/E30 -> 3.2009112 | F28: =+F27/F30 -> 6.7494608 | G28: =+G27/G30 -> 13.498922
C30: Diluted Shares | D30: 452984 | E30: 450169 | F30: =+E30 -> 450169 | G30: =+F30 -> 450169
C32: EBITDA | D32: =+D21+D73+D74 -> 5212593 | E32: =+E21+E73+E74 -> 4923136 | F32: =+F21+F73+F74 -> 10135729 | G32: =+G21+G73+G74 -> 20271458
C33: EBITDA Margin | D33: =+D32/D$6 -> 0.66252508 | E33: =+E32/E$6 -> 0.61769748 | F33: =+F32/F$6 -> 0.6399664 | G33: =+G32/G$6 -> 0.6399664
C36: Balance Sheet | D36: Q1-2022 | E36: Q2-2022
C37: Cash | D37: 6008946 | E37: 5819449
C38: Other current assets | D38: 2089069 | E38: 2021329
C39: Current Assets | D39: =+D37+D38 -> 8098015 | E39: =+E37+E38 -> 7840778
C41: Content assets | D41: 31191920 | E41: 32533199
C42: PP&E | D42: 1383763 | E42: 1361920
C43: Other non-current assets | D43: 4657206 | E43: 4615038
C44: Non-current Assets | D44: =+D41+D42+D43 -> 37232889 | E44: =+E41+E42+E43 -> 38510157
C46: Total Assets | D46: =+D39+D44 -> 45330904 | E46: =+E39+E44 -> 46350935
C48: Current content liabilities | D48: 4066289 | E48: 4174966
C49: Accounts payable | D49: 617202 | E49: 504278
C50: Accrued expenses and other liabilities | D50: 1817117 | E50: 1596035
C51: Deferred revenue | D51: 1239048 | E51: 1224743
C52: Short-term debt | D52: 0 | E52: 0
C53: Current Liabilities | D53: =+D48+D49+D50+D51+D52 -> 7739656 | E53: =+E48+E49+E50+E51+E52 -> 7500022
C55: Non-current content liabilities | D55: 2945221 | E55: 2989961
C56: Long-term debt | D56: 14534561 | E56: 14233303
C57: Other long-term liabilities | D57: 2567427 | E57: 2551675
C58: Non-current Liabilities | D58: =+D55+D56+D57 -> 20047209 | E58: =+E55+E56+E57 -> 19774939
C60: Equity | D60: 17544039 | E60: 19075974
C62: Total Equity & Liabilities | D62: =+D60+D58+D53 -> 45330904 | E62: =+E60+E58+E53 -> 46350935
C63: Check | D63: =+D46-D62 -> 0 | E63: =+E46-E62 -> 0
C65: Net Financial Debt | D65: =+D56-D37 -> 8525615 | E65: =+E56-E37 -> 8413854
C66: Net Working Capital | D66: =+D38-D48-D49-D50-D51-D55 -> -8595808 | E66: =+E38-E48-E49-E50-E51-E55 -> -8468654
C67: Total Finance Position | D67: =+D65-D66 -> 17121423 | E67: =+E65-E66 -> 16882508
C69: Cash Flow | D69: Q1-2022 | E69: Q2-2022 | F69: H1 2022 | G69: Run-rate
C70: Net income | D70: 1597447 | E70: 1440951
C71: Additions to content assets | D71: -3584164 | E71: -4687011 | F71: =+D71+E71 -> -8271175 | G71: =+F71*2 -> -16542350
C72: Change in content liabilities | D72: -347149 | E72: 191228
C73: Amortization of content assets | D73: 3166365 | E73: 3261348 | F73: =+D73+E73 -> 6427713 | G73: =+F73*2 -> 12855426
C74: D&A | D74: 74602 | E74: 83505 | F74: =+D74+E74 -> 158107 | G74: =+F74*2 -> 316214
C75: Stock-based compensation expense | D75: 119209 | E75: 150392
C76: Foreign currency remeasurement loss (gain) on debt | D76: -161821 | E76: -304513
C77: Other non-cash items | D77: 101968 | E77: 205374
C78: Deferred income taxes | D78: -68906 | E78: -115820
C79: Changes in Working Capital | D79: =SUM(D80:D84) -> 25288 | E79: -122704
C80: Change in other current assets | D80: 41157 | E80: 123399
C81: Change in accounts payable | D81: -215444 | E81: -122048
C82: Change in accrued expenses and other liabilities | D82: 350763 | E82: -238719
C83: Change in deferred revenue | D83: 16743 | E83: -10376
C84: Change in other non-current assets and liabilities | D84: -167931 | E84: 125040
C85: Operating Cash Flow | D85: =SUM(D70:D79) -> 922839 | E85: =SUM(E70:E79) -> 102750
C87: Purchase of PP&E | D87: -121158 | E87: -90018 | F87: =+D87+E87 -> -211176 | G87: =+F87*2 -> -422352
C88: Change in other assets | D88: 0 | E88: 0
C89: Acquisitions | D89: -124521 | E89: -68876
C90: Investing Cash Flow | D90: =SUM(D87:D89) -> -245679 | E90: =SUM(E87:E89) -> -158894
C92: Free Cash Flow | D92: =+D85+D90 -> 677160 | E92: =+E85+E90 -> -56144
C94: Repayments of debt | D94: -700000 | E94: 0
C95: Proceeds from issuance of common stock | D95: 13678 | E95: 11250
C96: Repurchases of common stock | D96: 0 | E96: 0
C97: Financing Cash Flow | D97: =SUM(D94:D96) -> -686322 | E97: =SUM(E94:E96) -> 11250
C99: FX | D99: -11448 | E99: -145198
C101: Total Cash Flow | D101: =+D92+D97+D99 -> -20610 | E101: =+E92+E97+E99 -> -190092
C103: Cash BoP | D103: 6055111 | E103: =+D104 -> 6034501
C104: Cash EoP | D104: =+D101+D103 -> 6034501 | E104: =+E101+E103 -> 5844409

Sheet Model
C2: Netflix | E2: SCENARIO SELECTION -> | H2: 1
C3: Model | H3: =IF(H2=1,"Base Case", IF(H2=2,"Bull Case", IF(H2=3,"Bear Case","-"))) -> Base Case
C5: Netflix | E5: SCENARIO SELECTION -> | H5: =+Valuation!M2 -> 1
C6: Financial Model | H6: =IF(H5=1,"Base Case", IF(H5=2,"Bull Case", IF(H5=3,"Bear Case","-"))) -> Base Case
C8: Netflix - in $ thousands | D8: 2017 | E8: =+D8+1 -> 2018 | F8: =+E8+1 -> 2019 | G8: =+F8+1 -> 2020 | H8: =+G8+1 -> 2021 | I8: =+H8+1 -> 2022 | J8: =+I8+1 -> 2023 | K8: =+J8+1 -> 2024 | L8: =+K8+1 -> 2025 | M8: =+L8+1 -> 2026 | N8: Afterwards
C9: Revenues United Estates & Canada | D9: 6660859 | E9: 8281532 | F9: 10051208 | G9: 11455396 | H9: 12972100 | I9: =+Assumptions!E7 -> 13893119 | J9: =+Assumptions!F7 -> 14879531 | K9: =+Assumptions!G7 -> 15935977 | L9: =+Assumptions!H7 -> 17067432 | M9: =+Assumptions!I7 -> 18279219
C10: Paid net membership additions | D10: 5512 | E10: 6335 | F10: 2905 | G10: 6274 | H10: 1279 | I10: =+I11-H11 -> 1504.3 | J10: =+J11-I11 -> 1534.386 | K10: =+K11-J11 -> 1565.0737 | L10: =+L11-K11 -> 1596.3752 | M10: =+M11-L11 -> 1628.3027
C11: Paid memberships at end of period | D11: 58422 | E11: 64757 | F11: 67662 | G11: 73936 | H11: 75215 | I11: =+Assumptions!E12 -> 76719.3 | J11: =+Assumptions!F12 -> 78253.686 | K11: =+Assumptions!G12 -> 79818.76 | L11: =+Assumptions!H12 -> 81415.135 | M11: =+Assumptions!I12 -> 83043.438
C12: Average price | D12: =+D9/D11 -> 114.01285 | E12: =+E9/E11 -> 127.88628 | F12: =+F9/F11 -> 148.55026 | G12: =+G9/G11 -> 154.93665 | H12: =+H9/H11 -> 172.46693 | I12: =+Assumptions!E22 -> 181.09027 | J12: =+Assumptions!F22 -> 190.14479 | K12: =+Assumptions!G22 -> 199.65203 | L12: =+Assumptions!H22 -> 209.63463 | M12: =+Assumptions!I22 -> 220.11636
C13: Average price growth as % | E13: =+E12/D12-1 -> 0.12168301 | F13: =+F12/E12-1 -> 0.16158091 | G13: =+G12/F12-1 -> 0.042991397 | H13: =+H12/G12-1 -> 0.11314483 | I13: =+I12/H12-1 -> 0.05 | J13: =+J12/I12-1 -> 0.05 | K13: =+K12/J12-1 -> 0.05 | L13: =+L12/K12-1 -> 0.05 | M13: =+M12/L12-1 -> 0.05
C14: Membership growth as % | E14: =+E11/D11-1 -> 0.10843518 | F14: =+F11/E11-1 -> 0.044860015 | G14: =+G11/F11-1 -> 0.092725607 | H14: =+H11/G11-1 -> 0.017298745 | I14: =+I11/H11-1 -> 0.02 | J14: =+J11/I11-1 -> 0.02 | K14: =+K11/J11-1 -> 0.02 | L14: =+L11/K11-1 -> 0.02 | M14: =+M11/L11-1 -> 0.02
C16: Revenues EMEA | D16: 2362813 | E16: 3963707 | F16: 5543067 | G16: 7772252 | H16: 9699819 | I16: =+Assumptions!E32 -> 10541278 | J16: =+Assumptions!F32 -> 11455734 | K16: =+Assumptions!G32 -> 12449519 | L16: =+Assumptions!H32 -> 13529515 | M16: =+Assumptions!I32 -> 14703200
C17: Paid net membership additions | D17: 8173 | E17: 11814 | F17: 13960 | G17: 14920 | H17: 7338 | I17: =+I18-H18 -> 3701.8 | J17: =+J18-I18 -> 3886.89 | K17: =+K18-J18 -> 4081.2345 | L17: =+L18-K18 -> 4285.2962 | M17: =+M18-L18 -> 4499.561
C18: Paid memberships at end of period | D18: 26004 | E18: 37818 | F18: 51778 | G18: 66698 | H18: 74036 | I18: =+Assumptions!E37 -> 77737.8 | J18: =+Assumptions!F37 -> 81624.69 | K18: =+Assumptions!G37 -> 85705.924 | L18: =+Assumptions!H37 -> 89991.221 | M18: =+Assumptions!I37 -> 94490.782
C19: Average price | D19: =+D16/D18 -> 90.863444 | E19: =+E16/E18 -> 104.81006 | F19: =+F16/F18 -> 107.05448 | G19: =+G16/G18 -> 116.52901 | H19: =+H16/H18 -> 131.0149 | I19: =+Assumptions!E47 -> 135.60042 | J19: =+Assumptions!F47 -> 140.34643 | K19: =+Assumptions!G47 -> 145.25856 | L19: =+Assumptions!H47 -> 150.34261 | M19: =+Assumptions!I47 -> 155.6046
C20: Average price growth as % | E20: =+E19/D19-1 -> 0.15348989 | F20: =+F19/E19-1 -> 0.021414152 | G20: =+G19/F19-1 -> 0.088501934 | H20: =+H19/G19-1 -> 0.12431142 | I20: =+I19/H19-1 -> 0.035 | J20: =+J19/I19-1 -> 0.035 | K20: =+K19/J19-1 -> 0.035 | L20: =+L19/K19-1 -> 0.035 | M20: =+M19/L19-1 -> 0.035
C21: Membership growth as % | E21: =+E18/D18-1 -> 0.45431472 | F21: =+F18/E18-1 -> 0.36913639 | G21: =+G18/F18-1 -> 0.28815327 | H21: =+H18/G18-1 -> 0.11001829 | I21: =+I18/H18-1 -> 0.05 | J21: =+J18/I18-1 -> 0.05 | K21: =+K18/J18-1 -> 0.05 | L21: =+L18/K18-1 -> 0.05 | M21: =+M18/L18-1 -> 0.05
C23: Revenues LATAM | D23: 1642616 | E23: 2237697 | F23: 2795434 | G23: 3156727 | H23: 3576976 | I23: =+Assumptions!E57 -> 3887278.7 | J23: =+Assumptions!F57 -> 4224500.1 | K23: =+Assumptions!G57 -> 4590975.5 | L23: =+Assumptions!H57 -> 4989242.6 | M23: =+Assumptions!I57 -> 5422059.4
C24: Paid net membership additions | D24: 5509 | E24: 6360 | F24: 5340 | G24: 6120 | H24: 2424 | I24: =+I25-H25 -> 1998.05 | J24: =+J25-I25 -> 2097.9525 | K24: =+K25-J25 -> 2202.8501 | L24: =+L25-K25 -> 2312.9926 | M24: =+M25-L25 -> 2428.6423
C25: Paid memberships at end of period | D25: 19717 | E25: 26077 | F25: 31417 | G25: 37537 | H25: 39961 | I25: =+Assumptions!E62 -> 41959.05 | J25: =+Assumptions!F62 -> 44057.003 | K25: =+Assumptions!G62 -> 46259.853 | L25: =+Assumptions!H62 -> 48572.845 | M25: =+Assumptions!I62 -> 51001.488
C26: Average price | D26: =+D23/D25 -> 83.309631 | E26: =+E23/E25 -> 85.811136 | F26: =+F23/F25 -> 88.978387 | G26: =+G23/G25 -> 84.096412 | H26: =+H23/H25 -> 89.511674 | I26: =+Assumptions!E72 -> 92.644582 | J26: =+Assumptions!F72 -> 95.887143 | K26: =+Assumptions!G72 -> 99.243193 | L26: =+Assumptions!H72 -> 102.7167 | M26: =+Assumptions!I72 -> 106.31179
C27: Average price growth as % | E27: =+E26/D26-1 -> 0.0300266 | F27: =+F26/E26-1 -> 0.03690956 | G27: =+G26/F26-1 -> -0.054866986 | H27: =+H26/G26-1 -> 0.064393501 | I27: =+I26/H26-1 -> 0.035 | J27: =+J26/I26-1 -> 0.035 | K27: =+K26/J26-1 -> 0.035 | L27: =+L26/K26-1 -> 0.035 | M27: =+M26/L26-1 -> 0.035
C28: Membership growth as % | E28: =+E25/D25-1 -> 0.32256428 | F28: =+F25/E25-1 -> 0.20477816 | G28: =+G25/F25-1 -> 0.19479899 | H28: =+H25/G25-1 -> 0.064576285 | I28: =+I25/H25-1 -> 0.05 | J28: =+J25/I25-1 -> 0.05 | K28: =+K25/J25-1 -> 0.05 | L28: =+L25/K25-1 -> 0.05 | M28: =+M25/L25-1 -> 0.05
C30: Revenues Asia-Pacific | D30: 575928 | E30: 945816 | F30: 1469521 | G30: 2372300 | H30: 3266601 | I30: =+Assumptions!E82 -> 3944420.7 | J30: =+Assumptions!F82 -> 4717527.2 | K30: =+Assumptions!G82 -> 5223482 | L30: =+Assumptions!H82 -> 5649195.7 | M30: =+Assumptions!I82 -> 5964138.4
C31: Paid net membership additions | D31: 2360 | E31: 4106 | F31: 5636 | G31: 9259 | H31: 7140 | I31: =+I32-H31 -> 30386.8 | J31: =+J32-I31 -> 12769.02 | K31: =+K32-J31 -> 33623.486 | L31: =+L32-K31 -> 15088.645 | M31: =+M32-L31 -> 34841.29
C32: Paid memberships at end of period | D32: 6501 | E32: 10607 | F32: 16233 | G32: 25492 | H32: 32632 | I32: =+Assumptions!E87 -> 37526.8 | J32: =+Assumptions!F87 -> 43155.82 | K32: =+Assumptions!G87 -> 46392.507 | L32: =+Assumptions!H87 -> 48712.132 | M32: =+Assumptions!I87 -> 49929.935
C33: Average price | D33: =+D30/D32 -> 88.590678 | E33: =+E30/E32 -> 89.169039 | F33: =+F30/F32 -> 90.526766 | G33: =+G30/G32 -> 93.060568 | H33: =+H30/H32 -> 100.10422 | I33: =+Assumptions!E97 -> 105.10943 | J33: =+Assumptions!F97 -> 109.31381 | K33: =+Assumptions!G97 -> 112.59323 | L33: =+Assumptions!H97 -> 115.97102 | M33: =+Assumptions!I97 -> 119.45015
C34: Average price growth as % | E34: =+E33/D33-1 -> 0.0065284629 | F34: =+F33/E33-1 -> 0.015226441 | G34: =+G33/F33-1 -> 0.027989529 | H34: =+H33/G33-1 -> 0.07568893 | I34: =+I33/H33-1 -> 0.05 | J34: =+J33/I33-1 -> 0.04 | K34: =+K33/J33-1 -> 0.03 | L34: =+L33/K33-1 -> 0.03 | M34: =+M33/L33-1 -> 0.03
C35: Membership growth as % | E35: =+E32/D32-1 -> 0.63159514 | F35: =+F32/E32-1 -> 0.53040445 | G35: =+G32/F32-1 -> 0.57038132 | H35: =+H32/G32-1 -> 0.28008787 | I35: =+I32/H32-1 -> 0.15 | J35: =+J32/I32-1 -> 0.15 | K35: =+K32/J32-1 -> 0.075 | L35: =+L32/K32-1 -> 0.05 | M35: =+M32/L32-1 -> 0.025
C37: Total Memberships Revenues | D37: =+D30+D23+D16+D9 -> 11242216 | E37: =+E30+E23+E16+E9 -> 15428752 | F37: =+F30+F23+F16+F9 -> 19859230 | G37: =+G30+G23+G16+G9 -> 24756675 | H37: =+H30+H23+H16+H9 -> 29515496 | I37: =+I30+I23+I16+I9 -> 32266097 | J37: =+J30+J23+J16+J9 -> 35277292 | K37: =+K30+K23+K16+K9 -> 38199954 | ... M37: =+M30+M23+M16+M9 -> 44368617
C38: Other Revenues | D38: =+D40-D37 -> 450497 | E38: =+E40-E37 -> 365589 | F38: =+F40-F37 -> 297217 | G38: =+G40-G37 -> 239381 | H38: =+H40-H37 -> 182348 | I38: =+Assumptions!E107 -> 136761 | J38: =+Assumptions!F107 -> 95732.7 | K38: =+Assumptions!G107 -> 62226.255 | L38: =+Assumptions!H107 -> 31113.127 | M38: =+Assumptions!I107 -> 0
C39: Other Revenues Growth as % | E39: =+E38/D38-1 -> -0.18847628 | F39: =+F38/E38-1 -> -0.18701876 | G39: =+G38/F38-1 -> -0.19459183 | H39: =+H38/G38-1 -> -0.23825199 | I39: =+I38/H38-1 -> -0.25 | J39: =+J38/I38-1 -> -0.3 | K39: =+K38/J38-1 -> -0.35 | L39: =+L38/K38-1 -> -0.5 | M39: =+M38/L38-1 -> -1
C40: Total Revenues | D40: 11692713 | E40: 15794341 | F40: 20156447 | G40: 24996056 | H40: 29697844 | I40: =+I38+I37 -> 32402858 | J40: =+J38+J37 -> 35373025 | K40: =+K38+K37 -> 38262180 | L40: =+L38+L37 -> 41266498 | M40: =+M38+M37 -> 44368617
C41: Total Revenue Growth | E41: =+E40/D40-1 -> 0.35078497 | F41: =+F40/E40-1 -> 0.27618158 | G41: =+G40/F40-1 -> 0.24010229 | H41: =+H40/G40-1 -> 0.18810119 | I41: =+I40/H40-1 -> 0.091084517 | J41: =+J40/I40-1 -> 0.091663734 | K41: =+K40/J40-1 -> 0.081676796 | L41: =+L40/K40-1 -> 0.078519257 | M41: =+M40/L40-1 -> 0.075172829
C43: COGS | D43: -8033000 | E43: -9967538 | F43: -12440213 | G43: -15276319 | H43: -17332683
C44: D&A of Content | D44: =+D104 -> 6197817 | E44: =+E104 -> 7532088 | F44: =+F104 -> 9216247 | G44: =+G104 -> 10806912 | H44: =+H104 -> 12230367
C45: D&A of PPE | D45: =+D105 -> 71911 | E45: =+E105 -> 83157 | F45: =+F105 -> 103579 | G45: =+G105 -> 115710 | H45: =+H105 -> 208412
C46: Adjusted COGS | D46: =+D44+D43+D45 -> -1763272 | E46: =+E44+E43+E45 -> -2352293 | F46: =+F44+F43+F45 -> -3120387 | G46: =+G44+G43+G45 -> -4353697 | H46: =+H44+H43+H45 -> -4893904 | I46: =-I40*Assumptions!E117 -> -4892831.5 | J46: =-J40*Assumptions!F117 -> -5341326.7 | K46: =-K40*Assumptions!G117 -> -5777589.2 | L46: =-L40*Assumptions!H117 -> -6231241.2 | M46: =-M40*Assumptions!I117 -> -6699661.2
C47: Gross Profit | D47: =+D40+D46 -> 9929441 | E47: =+E40+E46 -> 13442048 | F47: =+F40+F46 -> 17036060 | G47: =+G40+G46 -> 20642359 | H47: =+H40+H46 -> 24803940 | I47: =+I40+I46 -> 27510026 | J47: =+J40+J46 -> 30031698 | K47: =+K40+K46 -> 32484591 | ... M47: =+M40+M46 -> 37668956
C48: Gross Margin | D48: =IFERROR(+D47/D$40,"-") -> 0.84919907 | E48: =IFERROR(+E47/E$40,"-") -> 0.85106735 | F48: =IFERROR(+F47/F$40,"-") -> 0.84519162 | G48: =IFERROR(+G47/G$40,"-") -> 0.82582464 | H48: =IFERROR(+H47/H$40,"-") -> 0.83521013 | I48: =IFERROR(+I47/I$40,"-") -> 0.849 | J48: =IFERROR(+J47/J$40,"-") -> 0.849 | K48: =IFERROR(+K47/K$40,"-") -> 0.849 | ... M48: =IFERROR(+M47/M$40,"-") -> 0.849
C50: Marketing | D50: -1436281 | E50: -2369469 | F50: -2652462 | G50: -2228362 | H50: -2545146 | I50: =+I40*-Assumptions!E122 -> -2592228.6 | J50: =+J40*-Assumptions!F122 -> -2741409.4 | K50: =+K40*-Assumptions!G122 -> -2869663.5 | L50: =+L40*-Assumptions!H122 -> -2991821.1 | M50: =+M40*-Assumptions!I122 -> -3105803.2
C51: Marketing as % of revenues | D51: =-D50/D$40 -> 0.12283556 | E51: =-E50/E$40 -> 0.15002012 | F51: =-F50/F$40 -> 0.13159373 | G51: =-G50/G$40 -> 0.089148544 | H51: =-H50/H$40 -> 0.085701373 | I51: =-I50/I$40 -> 0.08 | J51: =-J50/J$40 -> 0.0775 | K51: =-K50/K$40 -> 0.075 | ... M51: =-M50/M$40 -> 0.07
C52: Technology and development | D52: -953710 | E52: -1221814 | F52: -1545149 | G52: -1829600 | H52: -2273885 | I52: =+I40*-Assumptions!E127 -> -2754242.9 | J52: =+J40*-Assumptions!F127 -> -2918274.5 | K52: =+K40*-Assumptions!G127 -> -3060974.4 | L52: =+L40*-Assumptions!H127 -> -3301319.8 | M52: =+M40*-Assumptions!I127 -> -3549489.4
C53: Technology and development as % of revenues | D53: =-D52/D$40 -> 0.081564475 | E53: =-E52/E$40 -> 0.077357707 | F53: =-F52/F$40 -> 0.076657806 | G53: =-G52/G$40 -> 0.073195547 | H53: =-H52/H$40 -> 0.076567343 | I53: =-I52/I$40 -> 0.085 | J53: =-J52/J$40 -> 0.0825 | K53: =-K52/K$40 -> 0.08 | ... M53: =-M52/M$40 -> 0.08
C54: G&A | D54: -431043 | E54: -630294 | F54: -914369 | G54: -1076486 | H54: -1351621 | I54: =+I40*-Assumptions!E132 -> -1458128.6 | J54: =+J40*-Assumptions!F132 -> -1680218.7 | K54: =+K40*-Assumptions!G132 -> -1817453.6 | L54: =+L40*-Assumptions!H132 -> -2063324.9 | M54: =+M40*-Assumptions!I132 -> -2218430.9
C55: G&A as % of revenues | D55: =-D54/D$40 -> 0.036864242 | E55: =-E54/E$40 -> 0.039906318 | F55: =-F54/F$40 -> 0.0453636 | G55: =-G54/G$40 -> 0.043066234 | H55: =-H54/H$40 -> 0.045512428 | I55: =-I54/I$40 -> 0.045 | J55: =-J54/J$40 -> 0.0475 | K55: =-K54/K$40 -> 0.0475 | ... M55: =-M54/M$40 -> 0.05
C56: EBITDA | D56: =+D47+D50+D52+D54 -> 7108407 | E56: =+E47+E50+E52+E54 -> 9220471 | F56: =+F47+F50+F52+F54 -> 11924080 | G56: =+G47+G50+G52+G54 -> 15507911 | H56: =+H47+H50+H52+H54 -> 18633288 | I56: =+I47+I50+I52+I54 -> 20705426 | J56: =+J47+J50+J52+J54 -> 22691795 | K56: =+K47+K50+K52+K54 -> 24736499 | ... M56: =+M47+M50+M52+M54 -> 28795233
C57: EBITDA Margin | D57: =IFERROR(+D56/D$40,"-") -> 0.60793479 | E57: =IFERROR(+E56/E$40,"-") -> 0.5837832 | F57: =IFERROR(+F56/F$40,"-") -> 0.59157648 | G57: =IFERROR(+G56/G$40,"-") -> 0.62041432 | H57: =IFERROR(+H56/H$40,"-") -> 0.62742898 | I57: =IFERROR(+I56/I$40,"-") -> 0.639 | J57: =IFERROR(+J56/J$40,"-") -> 0.6415 | K57: =IFERROR(+K56/K$40,"-") -> 0.6465 | ... M57: =IFERROR(+M56/M$40,"-") -> 0.649
C58: EBITDA Growth | E58: =+E56/D56-1 -> 0.29712199 | F58: =+F56/E56-1 -> 0.2932181 | G58: =+G56/F56-1 -> 0.30055409 | H58: =+H56/G56-1 -> 0.20153437 | I58: =+I56/H56-1 -> 0.11120625 | J58: =+J56/I56-1 -> 0.095934719 | K58: =+K56/J56-1 -> 0.090107637 | L58: =+L56/K56-1 -> 0.078519257 | M58: =+M56/L56-1 -> 0.079330496
C60: D&A | D60: =-D44-D45 -> -6269728 | E60: =-E44-E45 -> -7615245 | F60: =-F44-F45 -> -9319826 | G60: =-G44-G45 -> -10922622 | H60: =-H44-H45 -> -12438779 | I60: =-I156-I165 -> -12540821 | J60: =-J156-J165 -> -17262830 | K60: =-K156-K165 -> -22106994 | L60: =-L156-L165 -> -27076454 | M60: =-M156-M165 -> -19908315
C61: EBIT | D61: =+D56+D60 -> 838679 | E61: =+E56+E60 -> 1605226 | F61: =+F56+F60 -> 2604254 | G61: =+G56+G60 -> 4585289 | H61: =+H56+H60 -> 6194509 | I61: =+I56+I60 -> 8164605.4 | J61: =+J56+J60 -> 5428965.4 | K61: =+K56+K60 -> 2629505.8 | ... M61: =+M56+M60 -> 8886918.1
C62: EBIT Margin | D62: =IFERROR(+D61/D$40,"-") -> 0.071726639 | E62: =IFERROR(+E61/E$40,"-") -> 0.10163298 | F62: =IFERROR(+F61/F$40,"-") -> 0.12920204 | G62: =IFERROR(+G61/G$40,"-") -> 0.1834405 | H62: =IFERROR(+H61/H$40,"-") -> 0.20858447 | I62: =IFERROR(+I61/I$40,"-") -> 0.25197177 | J62: =IFERROR(+J61/J$40,"-") -> 0.15347756 | K62: =IFERROR(+K61/K$40,"-") -> 0.068723366 | ... M62: =IFERROR(+M61/M$40,"-") -> 0.20029739
C64: Interest expense | D64: -238204 | E64: -420493 | F64: -626023 | G64: -767499 | H64: -765620 | I64: =-I215 -> -701164.17 | J64: =-J215 -> -694747.5 | K64: =-K215 -> -677497.5 | L64: =-L215 -> -615493.33 | M64: =-M215 -> -586926.67
C65: Interest and other income | D65: -115154 | E65: 41725 | F65: 84000 | G65: -618441 | H65: 411214 | I65: 0 | J65: 0 | K65: 0 | L65: 0 | M65: 0
C66: Taxes | D66: 73608 | E66: -15216 | F66: -195315 | G66: -437954 | H66: -723875 | I66: =-(I61+I64+I65)*Assumptions!E197 -> -1865860.3 | J66: =-(J61+J64+J65)*Assumptions!F197 -> -1183554.5 | K66: =-(K61+K64+K65)*Assumptions!G197 -> -488002.07 | L66: =-(L61+L64+L65)*Assumptions!H197 -> 253288.98 | M66: =-(M61+M64+M65)*Assumptions!I197 -> -2074997.9
C67: Net Profit | D67: =+D61+SUM(D64:D66) -> 558929 | E67: =+E61+SUM(E64:E66) -> 1211242 | F67: =+F61+SUM(F64:F66) -> 1866916 | G67: =+G61+SUM(G64:G66) -> 2761395 | H67: =+H61+SUM(H64:H66) -> 5116228 | I67: =+I61+SUM(I64:I66) -> 5597580.9 | J67: =+J61+SUM(J64:J66) -> 3550663.4 | K67: =+K61+SUM(K64:K66) -> 1464006.2 | ... M67: =+M61+SUM(M64:M66) -> 6224993.6
C68: Net Profit Margin | D68: =IFERROR(+D67/D$40,"-") -> 0.047801481 | E68: =IFERROR(+E67/E$40,"-") -> 0.076688353 | F68: =IFERROR(+F67/F$40,"-") -> 0.092621284 | G68: =IFERROR(+G67/G$40,"-") -> 0.11047323 | H68: =IFERROR(+H67/H$40,"-") -> 0.17227608 | I68: =IFERROR(+I67/I$40,"-") -> 0.17274961 | J68: =IFERROR(+J67/J$40,"-") -> 0.10037772 | K68: =IFERROR(+K67/K$40,"-") -> 0.038262488 | ... M68: =IFERROR(+M67/M$40,"-") -> 0.14030173
C70: Balance Sheet | D70: 2017 | E70: =+D70+1 -> 2018 | F70: =+E70+1 -> 2019 | G70: =+F70+1 -> 2020 | H70: =+G70+1 -> 2021 | I70: =+H70+1 -> 2022 | J70: =+I70+1 -> 2023 | K70: =+J70+1 -> 2024 | L70: =+K70+1 -> 2025 | M70: =+L70+1 -> 2026
C71: Cash and cash equivalents | D71: 2822795 | E71: 3794483 | F71: 5018437 | G71: 8205550 | H71: 6027804 | I71: =+I246 -> 3000000 | J71: =+J246 -> 3000000 | K71: =+K246 -> 3000000 | L71: =+L246 -> 3000000 | M71: =+M246 -> 3000000
C72: Current content assets | D72: 4310934 | E72: 5151186 | F72: 0 | G72: 0 | H72: 0 | I72: 0 | J72: 0 | K72: 0 | L72: 0 | M72: 0
C73: Other current assets | D73: 536245 | E73: 748466 | F73: 1160067 | G73: 1556030 | H73: 2042021 | I73: =+I174 -> 2229316.6 | J73: =+J174 -> 2433664.1 | K73: =+K174 -> 2632438 | L73: =+L174 -> 2839135.1 | M73: =+M174 -> 3052560.9
C74: Current Assets | D74: =SUM(D71:D73) -> 7669974 | E74: =SUM(E71:E73) -> 9694135 | F74: =SUM(F71:F73) -> 6178504 | G74: =SUM(G71:G73) -> 9761580 | H74: =SUM(H71:H73) -> 8069825 | I74: =SUM(I71:I73) -> 5229316.6 | J74: =SUM(J71:J73) -> 5433664.1 | K74: =SUM(K71:K73) -> 5632438 | ... M74: =SUM(M71:M73) -> 6052560.9
C76: Content assets, net | D76: 10371055 | E76: 14951141 | F76: 24504567 | G76: 25383950 | H76: 30919539 | I76: =+H76+I139-I156 -> 36798222 | J76: =+I76+J139-J156 -> 38480930 | K76: =+J76+K139-K156 -> 35862764 | L76: =+K76+L139-L156 -> 28836201 | M76: =+L76+M139-M156 -> 29557106
C77: Property and equipment, net | D77: 319404 | E77: 418281 | F77: 565221 | G77: 960183 | H77: 1323453 | I77: =+H77+I145-I165 -> 1469943.4 | J77: =+I77+J145-J165 -> 1582630.8 | K77: =+J77+K145-K165 -> 1654547.4 | L77: =+K77+L145-L165 -> 1681039.9 | M77: =+L77+M145-M165 -> 1657029
C78: Other non-current assets | D78: 652309 | E78: 910843 | F78: 2727420 | G78: 3174646 | H78: 4271846 | I78: =+I168 -> 4374385.8 | J78: =+J168 -> 4775358.3 | K78: =+K168 -> 5165394.3 | L78: =+L168 -> 5570977.2 | M78: =+M168 -> 5989763.3
C79: Non-current Assets | D79: =+SUM(D76:D78) -> 11342768 | E79: =+SUM(E76:E78) -> 16280265 | F79: =+SUM(F76:F78) -> 27797208 | G79: =+SUM(G76:G78) -> 29518779 | H79: =+SUM(H76:H78) -> 36514838 | I79: =+SUM(I76:I78) -> 42642551 | J79: =+SUM(J76:J78) -> 44838919 | K79: =+SUM(K76:K78) -> 42682705 | ... M79: =+SUM(M76:M78) -> 37203898
C81: Total Assets | D81: =+D79+D74 -> 19012742 | E81: =+E79+E74 -> 25974400 | F81: =+F79+F74 -> 33975712 | G81: =+G79+G74 -> 39280359 | H81: =+H79+H74 -> 44584663 | I81: =+I79+I74 -> 47871868 | J81: =+J79+J74 -> 50272583 | K81: =+K79+K74 -> 48315143 | ... M81: =+M79+M74 -> 43256459
C83: Current content liabilities | D83: 4173041 | E83: 4681562 | F83: 4413561 | G83: 4429536 | H83: 4292967 | I83: 0 | J83: 0 | K83: 0 | L83: 0 | M83: 0
C84: Accounts payable | D84: 359555 | E84: 562985 | F84: 674347 | G84: 656183 | H84: 837483 | I84: =+I179 -> 804301.07 | J84: =+J179 -> 878026.31 | K84: =+K179 -> 949740.69 | L84: =+L179 -> 1024313.6 | M84: =+M179 -> 1101314.2
C85: Accrued expenses and other liabilities | D85: 315094 | E85: 481874 | F85: 843043 | G85: 1102196 | H85: 1449351 | I85: =+I182 -> 1620142.9 | J85: =+J182 -> 1768651.2 | K85: =+K182 -> 1913109 | L85: =+L182 -> 2063324.9 | M85: =+M182 -> 2218430.9
C86: Deferred revenue | D86: 618622 | E86: 760899 | F86: 924745 | G86: 1117992 | H86: 1209342 | I86: =+I185 -> 1296114.3 | J86: =+J185 -> 1414921 | K86: =+K185 -> 1530487.2 | L86: =+L185 -> 1650659.9 | M86: =+M185 -> 1774744.7
C87: Short-term debt | D87: 0 | E87: 0 | F87: 0 | G87: 499878 | H87: 699823 | I87: 0 | J87: 0 | K87: 0 | L87: 0 | M87: 0
C88: Current Liabilities | D88: =SUM(D83:D87) -> 5466312 | E88: =SUM(E83:E87) -> 6487320 | F88: =SUM(F83:F87) -> 6855696 | G88: =SUM(G83:G87) -> 7805785 | H88: =SUM(H83:H87) -> 8488966 | I88: =SUM(I83:I87) -> 3720558.3 | J88: =SUM(J83:J87) -> 4061598.5 | K88: =SUM(K83:K87) -> 4393336.9 | ... M88: =SUM(M83:M87) -> 5094489.7
C90: Non-current content liabilities | D90: 3329796 | E90: 3759026 | F90: 3334323 | G90: 2618084 | H90: 3094213 | I90: =+I193 -> 10936566 | J90: =+J193 -> 11209980 | K90: =+K193 -> 11490230 | L90: =+L193 -> 11777485 | M90: =+M193 -> 12071922
C91: Long-term debt | D91: 6499432 | E91: 10360058 | F91: 14759260 | G91: 15809095 | H91: 14693072 | I91: =+H87+H91-I205 -> 14692895 | J91: =+I87+I91-J205 -> 14692895 | K91: =+J87+J91-K205 -> 14292895 | L91: =+K87+K91-L205 -> 12457895 | M91: =+L87+L91-M205 -> 11457895
C92: Other non-current liabilities | D92: 135246 | E92: 129231 | F92: 1444276 | G92: 1982155 | H92: 2459164 | I92: =+I188 -> 2689437.2 | J92: =+J188 -> 2935961.1 | K92: =+K188 -> 3175760.9 | L92: =+L188 -> 3425119.3 | M92: =+M188 -> 3682595.2
C93: Non-current Liabilities | D93: =+SUM(D90:D92) -> 9964474 | E93: =+SUM(E90:E92) -> 14248315 | F93: =+SUM(F90:F92) -> 19537859 | G93: =+SUM(G90:G92) -> 20409334 | H93: =+SUM(H90:H92) -> 20246449 | I93: =+SUM(I90:I92) -> 28318898 | J93: =+SUM(J90:J92) -> 28838836 | K93: =+SUM(K90:K92) -> 28958885 | ... M93: =+SUM(M90:M92) -> 27212413
C95: Total Liabilities | D95: =+D93+D88 -> 15430786 | E95: =+E93+E88 -> 20735635 | F95: =+F93+F88 -> 26393555 | G95: =+G93+G88 -> 28215119 | H95: =+H93+H88 -> 28735415 | I95: =+I93+I88 -> 32039456 | J95: =+J93+J88 -> 32900435 | K95: =+K93+K88 -> 33352222 | ... M95: =+M93+M88 -> 32306902
C97: Equity | D97: 3581956 | E97: 5238765 | F97: 7582157 | G97: 11065240 | H97: 15849248 | I97: =+H97+I67+I239+I240+I241 -> 15832412 | J97: =+I97+J67+J239+J240+J241 -> 17372149 | K97: =+J97+K67+K239+K240+K241 -> 14962921 | L97: =+K97+L67+L239+L240+L241 -> 9528554.9 | M97: =+L97+M67+M239+M240+M241 -> 10949557
C98: Check | D98: =+D81-D95-D97 -> 0 | E98: =+E81-E95-E97 -> 0 | F98: =+F81-F95-F97 -> 0 | G98: =+G81-G95-G97 -> 0 | H98: =+H81-H95-H97 -> 0 | I98: =+I81-I95-I97 -> -9.3132257e-09 | J98: =+J81-J95-J97 -> -3.7252903e-09 | K98: =+K81-K95-K97 -> -3.7252903e-09 | ... M98: =+M81-M95-M97 -> -9.3132257e-09
C100: Cash Flow | D100: 2017 | E100: =+D100+1 -> 2018 | F100: =+E100+1 -> 2019 | G100: =+F100+1 -> 2020 | H100: =+G100+1 -> 2021 | I100: =+H100+1 -> 2022 | J100: =+I100+1 -> 2023 | K100: =+J100+1 -> 2024 | L100: =+K100+1 -> 2025 | M100: =+L100+1 -> 2026
C101: Net income | D101: =+D67 -> 558929 | E101: =+E67 -> 1211242 | F101: =+F67 -> 1866916 | G101: =+G67 -> 2761395 | H101: =+H67 -> 5116228
C102: Additions to content assets | D102: -9805763 | E102: -13043437 | F102: -13916683 | G102: -11779284 | H102: -17702202
C103: Change in content liabilities | D103: 900006 | E103: 999880 | F103: -694011 | G103: -757433 | H103: 232898
C104: Amortization of content assets | D104: 6197817 | E104: 7532088 | F104: 9216247 | G104: 10806912 | H104: 12230367
C105: Depreciation and amortization of PP&E | D105: 71911 | E105: 83157 | F105: 103579 | G105: 115710 | H105: 208412
C106: Stock-based compensation expense | D106: 182209 | E106: 320657 | F106: 405376 | G106: 415180 | H106: 403220
C107: Foreign currency remeasurement loss (gain) on debt | D107: 117864 | E107: 81640 | F107: 228230 | G107: 533278 | H107: -430661
C108: Other non-cash items | D108: 140790 | E108: -73953 | F108: -45576 | G108: 293126 | H108: 376777
C109: Deferred income taxes | D109: -208688 | E109: -85520 | F109: -94443 | G109: 70066 | H109: 199548
C110: Changes in Working Capital: | D110: =+SUM(D111:D115) -> 58977 | E110: =+SUM(E111:E115) -> 293767 | F110: =+SUM(F111:F115) -> 43043 | G110: =+SUM(G111:G115) -> -31873 | H110: =+SUM(H111:H115) -> -241977
C111: Other current assets | D111: -234090 | E111: -200192 | F111: -252113 | G111: -187623 | H111: -369681
C112: Accounts payable | D112: 74559 | E112: 199198 | F112: 96063 | G112: -41605 | H112: 145115
C113: Accrued expenses and other liabilities | D113: 114337 | E113: 150422 | F113: 157778 | G113: 198183 | H113: 180338
C114: Deferred revenue | D114: 177974 | E114: 142277 | F114: 163846 | G114: 193247 | H114: 91350
C115: Other non-current assets and liabilities | D115: -73803 | E115: 2062 | F115: -122531 | G115: -194075 | H115: -289099
C116: Cash flow from operating activities | D116: =+SUM(D101:D110) -> -1785948 | E116: =+SUM(E101:E110) -> -2680479 | F116: =+SUM(F101:F110) -> -2887322 | G116: =+SUM(G101:G110) -> 2427077 | H116: =+SUM(H101:H110) -> 392610
C118: Purchases of property and equipment | D118: -173302 | E118: -173946 | F118: -253035 | G118: -497923 | H118: -524585
C119: Change in other assets | D119: -60409 | E119: -165174 | F119: -134029 | G119: -7431 | H119: -26919
C120: Purchases of short-term investments | D120: -74819 | E120: 0 | F120: 0 | G120: 0 | H120: 0
...

Sheet Valuation
C2: Netflix | I2: SCENARIO SELECTION -> | M2: 1
C3: Valuation | M3: =IF(M2=1,"Base Case", IF(M2=2,"Bull Case", IF(M2=3,"Bear Case","-"))) -> Base Case
H4: 1 | I4: 1 | J4: =+I4+1 -> 2 | K4: =+J4+1 -> 3 | L4: =+K4+1 -> 4 | M4: =+L4+1 -> 5
C5: VALUATION | I5: 2022E | J5: 2023E | K5: 2024E | L5: 2025E | M5: 2026E | O5: Current Valuation Metrics (USD m) | P5: 2022E | R5: Valuation Metrics (USD m) | S5: FY 2021A | T5: FY 2022E | U5: FY 2023E | V5: FY 2024E
C6: EBITDA | I6: =+Model!I218 -> 20705426 | J6: =+Model!J218 -> 22691795 | K6: =+Model!K218 -> 24736499 | L6: =+Model!L218 -> 26678791 | M6: =+Model!M218 -> 28795233 | O6: #VALUE! | P6: {=_FV(O6,"Precio")} -> #NAME? | R6: Current Price | S6: =+$P$6 -> #NAME? | T6: =+$P$6 -> #NAME? | U6: =+$P$6 -> #NAME? | V6: =+$P$6 -> #NAME?
C7: Taxes | I7: =+Model!I219 -> -1865860.3 | J7: =+Model!J219 -> -1183554.5 | K7: =+Model!K219 -> -488002.07 | L7: =+Model!L219 -> 253288.98 | M7: =+Model!M219 -> -2074997.9
C8: Change in Working Capital | I8: =+Model!I222 -> 3586472.5 | J8: =+Model!J222 -> 410106.93 | K8: =+Model!K222 -> 413213.97 | L8: =+Model!L222 -> 425520.21 | M8: =+Model!M222 -> 437202.62 | O8: Shares outstading | P8: =+$M$24 -> 455372 | R8: Shares outstading | S8: =+$M$24 -> 455372 | T8: =+$M$24 -> 455372 | U8: =+$M$24 -> 455372 | V8: =+$M$24 -> 455372
C9: Other Balance Sheet Changes | I9: =+Model!I220+Model!I221 -> 127733.4 | J9: =+Model!J220+Model!J221 -> -154448.68 | K9: =+Model!K220+Model!K221 -> -150236.08 | L9: =+Model!L220+Model!L221 -> -156224.53 | M9: =+Model!M220+Model!M221 -> -161310.21 | O9: Market Cap | P9: =+P8*P6 -> #NAME? | R9: Market Cap | S9: =+S8*S6 -> #NAME? | T9: =+T8*T6 -> #NAME? | U9: =+U8*U6 -> #NAME? | V9: =+V8*V6 -> #NAME?
C10: Operating Cash Flow | I10: =SUM(I6:I9) -> 22553772 | J10: =SUM(J6:J9) -> 21763899 | K10: =SUM(K6:K9) -> 24511475 | L10: =SUM(L6:L9) -> 27201376 | M10: =SUM(M6:M9) -> 26996127 | O10: (+) Financial Debt | P10: =+Model!H91+Model!$H$87 -> 15392895 | R10: (+) Financial Debt | S10: =+$P$10 -> 15392895 | T10: =+$P$10 -> 15392895 | U10: =+$P$10 -> 15392895 | V10: =+$P$10 -> 15392895
O11: (-)/(+) Working Capital | P11: =+(Model!H72+Model!H73-Model!H83-Model!H84-Model!H85-Model!H86-Model!H90) -> -8841335 | R11: (-)/(+) Working Capital | S11: =+$P$11 -> -8841335 | T11: =+$P$11 -> -8841335 | U11: =+$P$11 -> -8841335 | V11: =+$P$11 -> -8841335
C12: Maintenance CapEx | I12: =+Model!I231+Model!I232 -> -18565994 | J12: =+Model!J231+Model!J232 -> -19058225 | K12: =+Model!K231+Model!K232 -> -19560744 | L12: =+Model!L231+Model!L232 -> -20076383 | M12: =+Model!M231+Model!M232 -> -20605209 | O12: (+) Other | P12: 0 | R12: (+) Other | S12: =+$P$12 -> 0 | T12: =+$P$12 -> 0 | U12: =+$P$12 -> 0 | V12: =+$P$12 -> 0
C13: Growth CapEx | O13: (-) Cash | P13: =-Model!H71 -> -6027804 | R13: (-) Cash | S13: =+$P$13 -> -6027804 | T13: =+$P$13 -> -6027804 | U13: =+$P$13 -> -6027804 | V13: =+$P$13 -> -6027804
C14: Free Cash Flow | I14: =+I10+I12+I13 -> 3987777.6 | J14: =+J10+J12+J13 -> 2705673.8 | K14: =+K10+K12+K13 -> 4950731.5 | L14: =+L10+L12+L13 -> 7124992.4 | M14: =+M10+M12+M13 -> 6390918.5 | O14: EV | P14: =+SUM(P9:P13) -> #NAME? | R14: EV | S14: =+SUM(S9:S13) -> #NAME? | T14: =+SUM(T9:T13) -> #NAME? | U14: =+SUM(U9:U13) -> #NAME? | V14: =+SUM(V9:V13) -> #NAME?
C15: WACC | G15: 0.25
C16: Discount Factor | I16: =1/(1+$G$15)^I4 -> 0.8 | J16: =1/(1+$G$15)^J4 -> 0.64 | K16: =1/(1+$G$15)^K4 -> 0.512 | L16: =1/(1+$G$15)^L4 -> 0.4096 | M16: =1/(1+$G$15)^M4 -> 0.32768 | O16: EBIT LTM | P16: =+Model!I61 -> 8164605.4 | R16: EBIT LTM | S16: =+Model!H61 -> 6194509 | T16: =+Model!I61 -> 8164605.4 | U16: =+Model!J61 -> 5428965.4 | V16: =+Model!K61 -> 2629505.8
O17: EV/EBIT | P17: =+P14/P16 -> #NAME? | R17: EV/EBIT | S17: =+S14/S16 -> #NAME? | T17: =+T14/T16 -> #NAME? | U17: =+U14/U16 -> #NAME? | V17: =+V14/V16 -> #NAME?
C18: Terminal Value - on FCF | G18: 15 | M18: =+M14*G18 -> 95863777
C19: UFCF plus TV | I19: =+I18+I14 -> 3987777.6 | J19: =+J18+J14 -> 2705673.8 | K19: =+K18+K14 -> 4950731.5 | L19: =+L18+L14 -> 7124992.4 | M19: =+M18+M14 -> 1.022547e+08 | O19: Net Profit LTM | P19: =+Model!I67 -> 5597580.9 | R19: Operating Cash Flow LTM | T19: =+I10 -> 22553772 | U19: =+J10 -> 21763899 | V19: =+K10 -> 24511475
C20: PV of UFCF plus TV | I20: =I19*I16 -> 3190222 | J20: =J19*J16 -> 1731631.2 | K20: =K19*K16 -> 2534774.5 | L20: =L19*L16 -> 2918396.9 | M20: =M19*M16 -> 33506819 | O20: PE | P20: =+P9/P19 -> #NAME? | R20: EV/OCF LTM | T20: =+T14/T19 -> #NAME? | U20: =+U14/U19 -> #NAME? | V20: =+V14/V19 -> #NAME?
C21: Enterprise Value | M21: =+SUM(I20:M20) -> 43881843 | O21: PE Ex-Cash | R21: EqV/OCF LTM | T21: =+T9/T19 -> #NAME? | U21: =+U9/U19 -> #NAME? | V21: =+V9/V19 -> #NAME?
C22: Less Current Net Debt at 31/12/2021 | M22: =-(Model!H87+Model!H91-Model!H71) -> -9365091
C23: Equity Value | M23: =+M22+M21 -> 34516752 | O23: EBITDA LTM | P23: =+Model!I56 -> 20705426 | R23: Normalized FCF | T23: =+I14-I13 -> 3987777.6 | U23: =+J14-J13 -> 2705673.8 | V23: =+K14-K13 -> 4950731.5
C24: Shares Outstanding | M24: 455372 | O24: EV/EBITDA LTM | P24: =+P14/P23 -> #NAME? | R24: Normalized FCF Yield | T24: =+T23/T9 -> #NAME? | U24: =+U23/U9 -> #NAME? | V24: =+V23/V9 -> #NAME?
C25: Equity Value per Share in USD | M25: =IFERROR(+M23/M24,0) -> 75.799022
C27: WACC and TV Multiple Impact on Equity Value per Share
I28: Exit TV Multiple
E29: =+M25 -> 75.799022 | F29: =+G29-1 -> 12 | G29: =+H29-1 -> 13 | H29: =+I29-1 -> 14 | I29: 15 | J29: =+I29+1 -> 16 | K29: =+J29+1 -> 17 | L29: =+K29+1 -> 18
E30: =E31-0.025 -> 0.2 | F30: 78.017141 | G30: 83.657292 | H30: 89.297443 | I30: 94.937594 | J30: 100.57775 | K30: 106.2179 | L30: 111.85805
D31: WACC | E31: =E32-0.025 -> 0.225 | F31: 69.544136 | G31: 74.631778 | H31: 79.719419 | I31: 84.807061 | J31: 89.894703 | K31: 94.982344 | L31: 100.06999
D32: Value | E32: 0.25 | F32: 62.002547 | G32: 66.601372 | H32: 71.200197 | I32: 75.799022 | J32: 80.397847 | K32: 84.996672 | L32: 89.595497
E33: =+E32+2.5% -> 0.275 | F33: 55.272542 | G33: 59.43784 | H33: 63.603138 | I33: 67.768435 | J33: 71.933733 | K33: 76.09903 | L33: 80.264328
E34: =+E33+2.5% -> 0.3 | F34: 49.251746 | G34: 53.031644 | H34: 56.811543 | I34: 60.591442 | J34: 64.371341 | K34: 68.15124 | L34: 71.931139
