Workbook

Sheet Assumptions
A1: SMG Swiss Marketplace Group Holding AG (SMG_SW) - Assumptions
A2: Scenario Selector: | G2: 1 | H2: 1=Base, 2=Bull, 3=Bear
C4: FY2023 | D4: FY2024 | E4: FY2025 | F4: FY2026 | G4: FY2027 | H4: FY2028 | I4: FY2029 | J4: FY2030
A6: Internet Content & Information
A7: Revenue ($M) | C7: 260.137 | D7: 290.879 | E7: 331.989
A8: Revenue Growth - Base | F8: 0.13 | G8: 0.12 | H8: 0.1 | I8: 0.08 | J8: 0.07
A9: Revenue Growth - Bull | F9: 0.16 | G9: 0.15 | H9: 0.13 | I9: 0.11 | J9: 0.09
A10: Revenue Growth - Bear | F10: 0.08 | G10: 0.06 | H10: 0.05 | I10: 0.04 | J10: 0.03
A11: Revenue Growth (Selected) | F11: =OFFSET(F8,$G$2-1,0) | G11: =OFFSET(G8,$G$2-1,0) | H11: =OFFSET(H8,$G$2-1,0) | I11: =OFFSET(I8,$G$2-1,0) | J11: =OFFSET(J8,$G$2-1,0)
A12: Revenue Projected ($M) | F12: =E7*(1+F11) | G12: =F12*(1+G11) | H12: =G12*(1+H11) | I12: =H12*(1+I11) | J12: =I12*(1+J11)
A14: Operating Assumptions
A15: Gross Margin - Base | F15: 0.48 | G15: 0.48 | H15: 0.48 | I15: 0.48 | J15: 0.48
A16: Gross Margin - Bull | F16: 0.54 | G16: 0.54 | H16: 0.54 | I16: 0.54 | J16: 0.54
A17: Gross Margin - Bear | F17: 0.4 | G17: 0.4 | H17: 0.4 | I17: 0.4 | J17: 0.4
A18: Gross Margin (Selected) | F18: =OFFSET(F15,$G$2-1,0) | G18: =OFFSET(G15,$G$2-1,0) | H18: =OFFSET(H15,$G$2-1,0) | I18: =OFFSET(I15,$G$2-1,0) | J18: =OFFSET(J15,$G$2-1,0)
A20: SG&A % Revenue - Base | F20: 0.1 | G20: 0.1 | H20: 0.1 | I20: 0.1 | J20: 0.1
A21: SG&A % Revenue - Bull | F21: 0.08 | G21: 0.08 | H21: 0.08 | I21: 0.08 | J21: 0.08
A22: SG&A % Revenue - Bear | F22: 0.12 | G22: 0.12 | H22: 0.12 | I22: 0.12 | J22: 0.12
A23: SG&A % Revenue (Selected) | F23: =OFFSET(F20,$G$2-1,0) | G23: =OFFSET(G20,$G$2-1,0) | H23: =OFFSET(H20,$G$2-1,0) | I23: =OFFSET(I20,$G$2-1,0) | J23: =OFFSET(J20,$G$2-1,0)
A25: R&D % Revenue - Base | F25: 0 | G25: 0 | H25: 0 | I25: 0 | J25: 0
A26: R&D % Revenue - Bull | F26: 0 | G26: 0 | H26: 0 | I26: 0 | J26: 0
A27: R&D % Revenue - Bear | F27: 0 | G27: 0 | H27: 0 | I27: 0 | J27: 0
A28: R&D % Revenue (Selected) | F28: =OFFSET(F25,$G$2-1,0) | G28: =OFFSET(G25,$G$2-1,0) | H28: =OFFSET(H25,$G$2-1,0) | I28: =OFFSET(I25,$G$2-1,0) | J28: =OFFSET(J25,$G$2-1,0)
A30: D&A % Revenue | F30: 0.18 | G30: 0.18 | H30: 0.18 | I30: 0.18 | J30: 0.18
A31: CapEx % Revenue | F31: 0.1 | G31: 0.1 | H31: 0.1 | I31: 0.1 | J31: 0.1
A32: Tax Rate | F32: 0.1 | G32: 0.1 | H32: 0.1 | I32: 0.1 | J32: 0.1
A34: Valuation Assumptions
A35: WACC - Base | C35: 0.1
A36: WACC - Bull | C36: 0.095
A37: WACC - Bear | C37: 0.11
A38: WACC (Selected) | C38: =OFFSET(C35,$G$2-1,0)
A40: Terminal Value Multiple - Base | C40: 18
A41: Terminal Value Multiple - Bull | C41: 22
A42: Terminal Value Multiple - Bear | C42: 14
A43: Terminal Value Multiple (Selected) | C43: =OFFSET(C40,$G$2-1,0)

Sheet Financial Statements
A1: SMG Swiss Marketplace Group Holding AG (SMG_SW) - Historical Financial Statements
A3: ($ in millions) | C3: FY2023 | D3: FY2024 | E3: FY2025
A5: Income Statement
A6: Total Revenue | C6: 260.137 | D6: 290.879 | E6: 331.989
A7: Cost of Revenue | C7: -19.278 | D7: -25.328 | E7: -26.854
A8: Gross Profit | C8: 279.415 | D8: 316.207 | E8: 358.843
A9: Gross Margin | C9: 1.0741071 | D9: 1.087074 | E9: 1.0808882
A11: R&D Expense | C11: 0 | D11: 0 | E11: 0
A12: SG&A Expense | C12: 28.237 | D12: 29.625 | E12: 29.982
A13: Operating Income (EBIT) | C13: 47.894 | D13: 71.036 | E13: 89.316
A14: EBIT Margin | C14: 0.18411068 | D14: 0.24421151 | E14: 0.26903301
A16: Interest Expense | C16: 1.518 | D16: 1.439 | E16: 3.723
A17: Tax Provision | C17: 0.132 | D17: 7.195 | E17: 16.334
A18: Net Income | C18: 46.098 | D18: 61.588 | E18: 67.694
A19: Net Margin | C19: 0.17720663 | D19: 0.21173065 | E19: 0.20390435
... A24: D&A | C24: 57.194 | D24: 59.22 | E24: 55.567
A27: Balance Sheet
A28: Cash & Equivalents | C28: 82.155 | D28: 71.485 | E28: 92.664
A29: Current Assets | C29: 123.8 | D29: 116.038 | E29: 147.016
A30: Net PP&E | C30: 18.679 | D30: 17.39 | E30: 14.54
A31: Goodwill | C31: 589.171 | D31: 628.2 | E31: 628.195
A32: Total Assets | C32: 1305.172 | D32: 1326.809 | E32: 1330.232
A34: Current Liabilities | C34: 98.212 | D34: 70.171 | E34: 102.688
A35: Total Debt | C35: 15.031 | D35: 13.645 | E35: 11.846
A36: Total Liabilities | C36: 211.949 | D36: 428.348 | E36: 425.501
A38: Total Equity | C38: 1093.223 | D38: 898.461 | E38: 904.731
A41: Cash Flow Statement
A42: Operating Cash Flow | C42: 91.862 | D42: 125.177 | E42: 140.498
A43: Capital Expenditure | C43: -28.439 | D43: -32.059 | E43: -33.87
A44: Free Cash Flow | C44: 63.423 | D44: 93.118 | E44: 106.628
A46: D&A | C46: 57.194 | D46: 59.22 | E46: 55.567
A47: Stock-Based Compensation | C47: 0.682 | D47: 0.836 | E47: 2.707
A48: Change in Working Capital | C48: -11.665 | D48: -5.36 | E48: -0.413

Sheet Model
A1: SMG Swiss Marketplace Group Holding AG (SMG_SW) - Financial Model
A2: Scenario: | C2: =Assumptions!G2
A4: ($M) | C4: FY2023 | D4: FY2024 | E4: FY2025 | F4: FY2026 | G4: FY2027 | H4: FY2028 | I4: FY2029 | J4: FY2030
F5: Proj. | G5: Proj. | H5: Proj. | I5: Proj. | J5: Proj.
A7: Revenue by Segment
A8: Internet Content & Information | C8: 260.137 | D8: 290.879 | E8: 331.989 | F8: =Assumptions!F12 | G8: =Assumptions!G12 | H8: =Assumptions!H12 | I8: =Assumptions!I12 | J8: =Assumptions!J12
A9: YoY Growth | D9: =IFERROR(D8/C8-1,"-") | E9: =IFERROR(E8/D8-1,"-") | F9: =IFERROR(F8/E8-1,"-") | G9: =IFERROR(G8/F8-1,"-") | H9: =IFERROR(H8/G8-1,"-") | I9: =IFERROR(I8/H8-1,"-") | J9: =IFERROR(J8/I8-1,"-")
A11: Total Revenue | C11: =C8 | D11: =D8 | E11: =E8 | F11: =F8 | G11: =G8 | H11: =H8 | I11: =I8 | J11: =J8
A12: Revenue Growth % | D12: =IFERROR(D11/C11-1,"-") | E12: =IFERROR(E11/D11-1,"-") | F12: =IFERROR(F11/E11-1,"-") | G12: =IFERROR(G11/F11-1,"-") | H12: =IFERROR(H11/G11-1,"-") | I12: =IFERROR(I11/H11-1,"-") | J12: =IFERROR(J11/I11-1,"-")
A14: Profit & Loss
A15: Revenue | C15: =C11 | D15: =D11 | E15: =E11 | F15: =F11 | G15: =G11 | H15: =H11 | I15: =I11 | J15: =J11
A16: Cost of Goods Sold (COGS) | C16: -19.278 | D16: -25.328 | E16: -26.854 | F16: =-F15*(1-Assumptions!F18) | G16: =-G15*(1-Assumptions!G18) | H16: =-H15*(1-Assumptions!H18) | I16: =-I15*(1-Assumptions!I18) | J16: =-J15*(1-Assumptions!J18)
A17: Gross Profit | C17: =C15+C16 | D17: =D15+D16 | E17: =E15+E16 | F17: =F15+F16 | G17: =G15+G16 | H17: =H15+H16 | I17: =I15+I16 | J17: =J15+J16
A18: Gross Margin % | C18: =IFERROR(C17/C15,"-") | D18: =IFERROR(D17/D15,"-") | E18: =IFERROR(E17/E15,"-") | F18: =IFERROR(F17/F15,"-") | G18: =IFERROR(G17/G15,"-") | H18: =IFERROR(H17/H15,"-") | I18: =IFERROR(I17/I15,"-") | J18: =IFERROR(J17/J15,"-")
A20: SG&A Expense | C20: 28.237 | D20: 29.625 | E20: 29.982 | F20: =-F15*Assumptions!F24 | G20: =-G15*Assumptions!G24 | H20: =-H15*Assumptions!H24 | I20: =-I15*Assumptions!I24 | J20: =-J15*Assumptions!J24
A21: R&D Expense | C21: 0 | D21: 0 | E21: 0 | F21: =-F15*Assumptions!F30 | G21: =-G15*Assumptions!G30 | H21: =-H15*Assumptions!H30 | I21: =-I15*Assumptions!I30 | J21: =-J15*Assumptions!J30
A22: Depreciation & Amortization | C22: 57.194 | D22: 59.22 | E22: 55.567 | F22: =-F15*Assumptions!F32 | G22: =-G15*Assumptions!G32 | H22: =-H15*Assumptions!H32 | I22: =-I15*Assumptions!I32 | J22: =-J15*Assumptions!J32
A24: EBITDA | C24: =C17+C20+C21 | D24: =D17+D20+D21 | E24: =E17+E20+E21 | F24: =F17+F20+F21 | G24: =G17+G20+G21 | H24: =H17+H20+H21 | I24: =I17+I20+I21 | J24: =J17+J20+J21
A25: EBITDA Margin % | C25: =IFERROR(C24/C15,"-") | D25: =IFERROR(D24/D15,"-") | E25: =IFERROR(E24/E15,"-") | F25: =IFERROR(F24/F15,"-") | G25: =IFERROR(G24/G15,"-") | H25: =IFERROR(H24/H15,"-") | I25: =IFERROR(I24/I15,"-") | J25: =IFERROR(J24/J15,"-")
A26: EBIT | C26: =C24+C22 | D26: =D24+D22 | E26: =E24+E22 | F26: =F24+F22 | G26: =G24+G22 | H26: =H24+H22 | I26: =I24+I22 | J26: =J24+J22
A27: EBIT Margin % | C27: =IFERROR(C26/C15,"-") | D27: =IFERROR(D26/D15,"-") | E27: =IFERROR(E26/E15,"-") | F27: =IFERROR(F26/F15,"-") | G27: =IFERROR(G26/G15,"-") | H27: =IFERROR(H26/H15,"-") | I27: =IFERROR(I26/I15,"-") | J27: =IFERROR(J26/J15,"-")
A29: Interest Expense | C29: 1.518 | D29: 1.439 | E29: 3.723 | F29: 3.723 | G29: 3.723 | H29: 3.723 | I29: 3.723 | J29: 3.723
A30: Earnings Before Tax (EBT) | C30: =C26+C29 | D30: =D26+D29 | E30: =E26+E29 | F30: =F26+F29 | G30: =G26+G29 | H30: =H26+H29 | I30: =I26+I29 | J30: =J26+J29
A31: Taxes | C31: 0.132 | D31: 7.195 | E31: 16.334 | F31: =-ABS(F30)*Assumptions!F34 | G31: =-ABS(G30)*Assumptions!G34 | H31: =-ABS(H30)*Assumptions!H34 | I31: =-ABS(I30)*Assumptions!I34 | J31: =-ABS(J30)*Assumptions!J34
A32: Net Income | C32: =C30+C31 | D32: =D30+D31 | E32: =E30+E31 | F32: =F30+F31 | G32: =G30+G31 | H32: =H30+H31 | I32: =I30+I31 | J32: =J30+J31
A33: Net Margin % | C33: =IFERROR(C32/C15,"-") | D33: =IFERROR(D32/D15,"-") | E33: =IFERROR(E32/E15,"-") | F33: =IFERROR(F32/F15,"-") | G33: =IFERROR(G32/G15,"-") | H33: =IFERROR(H32/H15,"-") | I33: =IFERROR(I32/I15,"-") | J33: =IFERROR(J32/J15,"-")
A36: Cash Flow
A37: EBITDA | C37: =C24 | D37: =D24 | E37: =E24 | F37: =F24 | G37: =G24 | H37: =H24 | I37: =I24 | J37: =J24
A38: (-) Taxes | C38: =C31 | D38: =D31 | E38: =E31 | F38: =F31 | G38: =G31 | H38: =H31 | I38: =I31 | J38: =J31
A39: (+/-) Change in Working Capital | C39: -11.665 | D39: -5.36 | E39: -0.413 | F39: 0 | G39: 0 | H39: 0 | I39: 0 | J39: 0
A40: Operating Cash Flow | C40: =C37+C38+C39 | D40: =D37+D38+D39 | E40: =E37+E38+E39 | F40: =F37+F38+F39 | G40: =G37+G38+G39 | H40: =H37+H38+H39 | I40: =I37+I38+I39 | J40: =J37+J38+J39
A42: (-) Capital Expenditure | C42: -28.439 | D42: -32.059 | E42: -33.87 | F42: =-ABS(F15)*Assumptions!F33 | G42: =-ABS(G15)*Assumptions!G33 | H42: =-ABS(H15)*Assumptions!H33 | I42: =-ABS(I15)*Assumptions!I33 | J42: =-ABS(J15)*Assumptions!J33
A43: Unlevered Free Cash Flow (UFCF) | C43: =C40+C42 | D43: =D40+D42 | E43: =E40+E42 | F43: =F40+F42 | G43: =G40+G42 | H43: =H40+H42 | I43: =I40+I42 | J43: =J40+J42
A200: __REF_EBITDA_ROW | B200: 24
A201: __REF_TAXES_ROW | B201: 31
A202: __REF_CAPEX_ROW | B202: 42
A203: __REF_UFCF_ROW | B203: 43
A204: __REF_WC_ROW | B204: 39
A205: __REF_NI_ROW | B205: 32
A206: __REF_TOTAL_REV_ROW | B206: 11

Sheet Valuation
A1: SMG Swiss Marketplace Group Holding AG (SMG_SW) - DCF Valuation
A2: Scenario: | C2: =Assumptions!G2 | E2: Current Price: | F2: 28.55
A4: Year | F4: 2026 | G4: 2027 | H4: 2028 | I4: 2029 | J4: 2030
A5: Year # | F5: 1 | G5: 2 | H5: 3 | I5: 4 | J5: 5
A7: DCF Inputs (from Model)
A8: EBITDA ($M) | F8: =INDIRECT("Model!"&"F"&Model!B200) | G8: =INDIRECT("Model!"&"G"&Model!B200) | H8: =INDIRECT("Model!"&"H"&Model!B200) | I8: =INDIRECT("Model!"&"I"&Model!B200) | J8: =INDIRECT("Model!"&"J"&Model!B200)
A9: (-) Taxes ($M) | F9: =INDIRECT("Model!"&"F"&Model!B201) | G9: =INDIRECT("Model!"&"G"&Model!B201) | H9: =INDIRECT("Model!"&"H"&Model!B201) | I9: =INDIRECT("Model!"&"I"&Model!B201) | J9: =INDIRECT("Model!"&"J"&Model!B201)
A10: (+/-) Change in WC ($M) | F10: =INDIRECT("Model!"&"F"&Model!B204) | G10: =INDIRECT("Model!"&"G"&Model!B204) | H10: =INDIRECT("Model!"&"H"&Model!B204) | I10: =INDIRECT("Model!"&"I"&Model!B204) | J10: =INDIRECT("Model!"&"J"&Model!B204)
A11: (-) CapEx ($M) | F11: =INDIRECT("Model!"&"F"&Model!B202) | G11: =INDIRECT("Model!"&"G"&Model!B202) | H11: =INDIRECT("Model!"&"H"&Model!B202) | I11: =INDIRECT("Model!"&"I"&Model!B202) | J11: =INDIRECT("Model!"&"J"&Model!B202)
A12: Unlevered Free Cash Flow ($M) | F12: =F8+F9+F10+F11 | G12: =G8+G9+G10+G11 | H12: =H8+H9+H10+H11 | I12: =I8+I9+I10+I11 | J12: =J8+J9+J10+J11
A14: Discounted Cash Flow
A15: WACC | C15: =Assumptions!C42
A16: Terminal Value Multiple | C16: =Assumptions!C48
A18: Discount Factor | F18: =1/(1+$C$15)^1 | G18: =1/(1+$C$15)^2 | H18: =1/(1+$C$15)^3 | I18: =1/(1+$C$15)^4 | J18: =1/(1+$C$15)^5
A19: PV of UFCF ($M) | F19: =F12*F18 | G19: =G12*G18 | H19: =H12*H18 | I19: =I12*I18 | J19: =J12*J18
A21: Terminal Value ($M) | J21: =J8*$C$16
A22: PV of Terminal Value ($M) | J22: =J21*J18
A24: Valuation Summary
A25: Sum of PV of UFCF ($M) | C25: =SUM(F19:J19)
A26: PV of Terminal Value ($M) | C26: =J22
A27: Enterprise Value ($M) | C27: =C25+C26
A29: (-) Net Debt ($M) | C29: 80.818
A30: Equity Value ($M) | C30: =C27+C29
A32: Shares Outstanding (M) | C32: 98.085188
A33: Equity Value per Share ($) | C33: =C30/C32
A34: Upside / Downside vs Current | C34: =C33/28.55-1
A37: Sensitivity Analysis: WACC vs Terminal Value Multiple
A38: WACC \ TV Multiple | C38: 14x | D38: 16x | E38: 18x | F38: 20x | G38: 22x
A39: 0.07 | C39: =(F$12/(1+$A$39)^1+G$12/(1+$A$39)^2+H$12/(1+$A$39)^3+I$12/(1+$A$39)^4+J$12/(1+$A$39)^5+J$8*14/(1+$A$39)^5+$C$29)/$C$32 | D39: =(F$12/(1+$A$39)^1+G$12/(1+$A$39)^2+H$12/(1+$A$39)^3+I$12/(1+$A$39)^4+J$12/(1+$A$39)^5+J$8*16/(1+$A$39)^5+$C$29)/$C$32 | E39: =(F$12/(1+$A$39)^1+G$12/(1+$A$39)^2+H$12/(1+$A$39)^3+I$12/(1+$A$39)^4+J$12/(1+$A$39)^5+J$8*18/(1+$A$39)^5+$C$29)/$C$32 | F39: =(F$12/(1+$A$39)^1+G$12/(1+$A$39)^2+H$12/(1+$A$39)^3+I$12/(1+$A$39)^4+J$12/(1+$A$39)^5+J$8*20/(1+$A$39)^5+$C$29)/$C$32 | G39: =(F$12/(1+$A$39)^1+G$12/(1+$A$39)^2+H$12/(1+$A$39)^3+I$12/(1+$A$39)^4+J$12/(1+$A$39)^5+J$8*22/(1+$A$39)^5+$C$29)/$C$32
A40: 0.08 | C40: =(F$12/(1+$A$40)^1+G$12/(1+$A$40)^2+H$12/(1+$A$40)^3+I$12/(1+$A$40)^4+J$12/(1+$A$40)^5+J$8*14/(1+$A$40)^5+$C$29)/$C$32 | D40: =(F$12/(1+$A$40)^1+G$12/(1+$A$40)^2+H$12/(1+$A$40)^3+I$12/(1+$A$40)^4+J$12/(1+$A$40)^5+J$8*16/(1+$A$40)^5+$C$29)/$C$32 | E40: =(F$12/(1+$A$40)^1+G$12/(1+$A$40)^2+H$12/(1+$A$40)^3+I$12/(1+$A$40)^4+J$12/(1+$A$40)^5+J$8*18/(1+$A$40)^5+$C$29)/$C$32 | F40: =(F$12/(1+$A$40)^1+G$12/(1+$A$40)^2+H$12/(1+$A$40)^3+I$12/(1+$A$40)^4+J$12/(1+$A$40)^5+J$8*20/(1+$A$40)^5+$C$29)/$C$32 | G40: =(F$12/(1+$A$40)^1+G$12/(1+$A$40)^2+H$12/(1+$A$40)^3+I$12/(1+$A$40)^4+J$12/(1+$A$40)^5+J$8*22/(1+$A$40)^5+$C$29)/$C$32
A41: 0.09 | C41: =(F$12/(1+$A$41)^1+G$12/(1+$A$41)^2+H$12/(1+$A$41)^3+I$12/(1+$A$41)^4+J$12/(1+$A$41)^5+J$8*14/(1+$A$41)^5+$C$29)/$C$32 | D41: =(F$12/(1+$A$41)^1+G$12/(1+$A$41)^2+H$12/(1+$A$41)^3+I$12/(1+$A$41)^4+J$12/(1+$A$41)^5+J$8*16/(1+$A$41)^5+$C$29)/$C$32 | E41: =(F$12/(1+$A$41)^1+G$12/(1+$A$41)^2+H$12/(1+$A$41)^3+I$12/(1+$A$41)^4+J$12/(1+$A$41)^5+J$8*18/(1+$A$41)^5+$C$29)/$C$32 | F41: =(F$12/(1+$A$41)^1+G$12/(1+$A$41)^2+H$12/(1+$A$41)^3+I$12/(1+$A$41)^4+J$12/(1+$A$41)^5+J$8*20/(1+$A$41)^5+$C$29)/$C$32 | G41: =(F$12/(1+$A$41)^1+G$12/(1+$A$41)^2+H$12/(1+$A$41)^3+I$12/(1+$A$41)^4+J$12/(1+$A$41)^5+J$8*22/(1+$A$41)^5+$C$29)/$C$32
A42: 0.1 | C42: =(F$12/(1+$A$42)^1+G$12/(1+$A$42)^2+H$12/(1+$A$42)^3+I$12/(1+$A$42)^4+J$12/(1+$A$42)^5+J$8*14/(1+$A$42)^5+$C$29)/$C$32 | D42: =(F$12/(1+$A$42)^1+G$12/(1+$A$42)^2+H$12/(1+$A$42)^3+I$12/(1+$A$42)^4+J$12/(1+$A$42)^5+J$8*16/(1+$A$42)^5+$C$29)/$C$32 | E42: =(F$12/(1+$A$42)^1+G$12/(1+$A$42)^2+H$12/(1+$A$42)^3+I$12/(1+$A$42)^4+J$12/(1+$A$42)^5+J$8*18/(1+$A$42)^5+$C$29)/$C$32 | F42: =(F$12/(1+$A$42)^1+G$12/(1+$A$42)^2+H$12/(1+$A$42)^3+I$12/(1+$A$42)^4+J$12/(1+$A$42)^5+J$8*20/(1+$A$42)^5+$C$29)/$C$32 | G42: =(F$12/(1+$A$42)^1+G$12/(1+$A$42)^2+H$12/(1+$A$42)^3+I$12/(1+$A$42)^4+J$12/(1+$A$42)^5+J$8*22/(1+$A$42)^5+$C$29)/$C$32
A43: 0.11 | C43: =(F$12/(1+$A$43)^1+G$12/(1+$A$43)^2+H$12/(1+$A$43)^3+I$12/(1+$A$43)^4+J$12/(1+$A$43)^5+J$8*14/(1+$A$43)^5+$C$29)/$C$32 | D43: =(F$12/(1+$A$43)^1+G$12/(1+$A$43)^2+H$12/(1+$A$43)^3+I$12/(1+$A$43)^4+J$12/(1+$A$43)^5+J$8*16/(1+$A$43)^5+$C$29)/$C$32 | E43: =(F$12/(1+$A$43)^1+G$12/(1+$A$43)^2+H$12/(1+$A$43)^3+I$12/(1+$A$43)^4+J$12/(1+$A$43)^5+J$8*18/(1+$A$43)^5+$C$29)/$C$32 | F43: =(F$12/(1+$A$43)^1+G$12/(1+$A$43)^2+H$12/(1+$A$43)^3+I$12/(1+$A$43)^4+J$12/(1+$A$43)^5+J$8*20/(1+$A$43)^5+$C$29)/$C$32 | G43: =(F$12/(1+$A$43)^1+G$12/(1+$A$43)^2+H$12/(1+$A$43)^3+I$12/(1+$A$43)^4+J$12/(1+$A$43)^5+J$8*22/(1+$A$43)^5+$C$29)/$C$32
A44: 0.12 | C44: =(F$12/(1+$A$44)^1+G$12/(1+$A$44)^2+H$12/(1+$A$44)^3+I$12/(1+$A$44)^4+J$12/(1+$A$44)^5+J$8*14/(1+$A$44)^5+$C$29)/$C$32 | D44: =(F$12/(1+$A$44)^1+G$12/(1+$A$44)^2+H$12/(1+$A$44)^3+I$12/(1+$A$44)^4+J$12/(1+$A$44)^5+J$8*16/(1+$A$44)^5+$C$29)/$C$32 | E44: =(F$12/(1+$A$44)^1+G$12/(1+$A$44)^2+H$12/(1+$A$44)^3+I$12/(1+$A$44)^4+J$12/(1+$A$44)^5+J$8*18/(1+$A$44)^5+$C$29)/$C$32 | F44: =(F$12/(1+$A$44)^1+G$12/(1+$A$44)^2+H$12/(1+$A$44)^3+I$12/(1+$A$44)^4+J$12/(1+$A$44)^5+J$8*20/(1+$A$44)^5+$C$29)/$C$32 | G44: =(F$12/(1+$A$44)^1+G$12/(1+$A$44)^2+H$12/(1+$A$44)^3+I$12/(1+$A$44)^4+J$12/(1+$A$44)^5+J$8*22/(1+$A$44)^5+$C$29)/$C$32
A45: 0.13 | C45: =(F$12/(1+$A$45)^1+G$12/(1+$A$45)^2+H$12/(1+$A$45)^3+I$12/(1+$A$45)^4+J$12/(1+$A$45)^5+J$8*14/(1+$A$45)^5+$C$29)/$C$32 | D45: =(F$12/(1+$A$45)^1+G$12/(1+$A$45)^2+H$12/(1+$A$45)^3+I$12/(1+$A$45)^4+J$12/(1+$A$45)^5+J$8*16/(1+$A$45)^5+$C$29)/$C$32 | E45: =(F$12/(1+$A$45)^1+G$12/(1+$A$45)^2+H$12/(1+$A$45)^3+I$12/(1+$A$45)^4+J$12/(1+$A$45)^5+J$8*18/(1+$A$45)^5+$C$29)/$C$32 | F45: =(F$12/(1+$A$45)^1+G$12/(1+$A$45)^2+H$12/(1+$A$45)^3+I$12/(1+$A$45)^4+J$12/(1+$A$45)^5+J$8*20/(1+$A$45)^5+$C$29)/$C$32 | G45: =(F$12/(1+$A$45)^1+G$12/(1+$A$45)^2+H$12/(1+$A$45)^3+I$12/(1+$A$45)^4+J$12/(1+$A$45)^5+J$8*22/(1+$A$45)^5+$C$29)/$C$32
