Workbook

Sheet Assumptions
A1: Netskope, Inc. (NTSK) - Assumptions
A2: Scenario Selector: | G2: 1 | H2: 1=Base, 2=Bull, 3=Bear
C4: FY2024 | D4: FY2025 | E4: FY2026 | F4: FY2027 | G4: FY2028 | H4: FY2029 | I4: FY2030
A6: Software - Infrastructure
A7: Revenue ($M) | C7: 406.883 | D7: 538.268
A8: Revenue Growth - Base | E8: 0.322 | F8: 0.2898 | G8: 0.2576 | H8: 0.2254 | I8: 0.1932
A9: Revenue Growth - Bull | E9: 0.4186 | F9: 0.37674 | G9: 0.33488 | H9: 0.29302 | I9: 0.25116
A10: Revenue Growth - Bear | E10: 0.2254 | F10: 0.20286 | G10: 0.18032 | H10: 0.15778 | I10: 0.13524
A11: Revenue Growth (Selected) | E11: =OFFSET(E8,$G$2-1,0) | F11: =OFFSET(F8,$G$2-1,0) | G11: =OFFSET(G8,$G$2-1,0) | H11: =OFFSET(H8,$G$2-1,0) | I11: =OFFSET(I8,$G$2-1,0)
A12: Revenue Projected ($M) | E12: =D7*(1+E11) | F12: =E12*(1+F11) | G12: =F12*(1+G11) | H12: =G12*(1+H11) | I12: =H12*(1+I11)
A14: Operating Assumptions
A15: Gross Margin - Base | E15: 0.62208408 | F15: 0.62208408 | G15: 0.62208408 | H15: 0.62208408 | I15: 0.62208408
A16: Gross Margin - Bull | E16: 0.64208408 | F16: 0.64208408 | G16: 0.64208408 | H16: 0.64208408 | I16: 0.64208408
A17: Gross Margin - Bear | E17: 0.60208408 | F17: 0.60208408 | G17: 0.60208408 | H17: 0.60208408 | I17: 0.60208408
A18: Gross Margin (Selected) | E18: =OFFSET(E15,$G$2-1,0) | F18: =OFFSET(F15,$G$2-1,0) | G18: =OFFSET(G15,$G$2-1,0) | H18: =OFFSET(H15,$G$2-1,0) | I18: =OFFSET(I15,$G$2-1,0)
A20: SG&A % Revenue - Base | E20: 0.73203605 | F20: 0.73203605 | G20: 0.73203605 | H20: 0.73203605 | I20: 0.73203605
A21: SG&A % Revenue - Bull | E21: 0.72203605 | F21: 0.72203605 | G21: 0.72203605 | H21: 0.72203605 | I21: 0.72203605
A22: SG&A % Revenue - Bear | E22: 0.74203605 | F22: 0.74203605 | G22: 0.74203605 | H22: 0.74203605 | I22: 0.74203605
A23: SG&A % Revenue (Selected) | E23: =OFFSET(E20,$G$2-1,0) | F23: =OFFSET(F20,$G$2-1,0) | G23: =OFFSET(G20,$G$2-1,0) | H23: =OFFSET(H20,$G$2-1,0) | I23: =OFFSET(I20,$G$2-1,0)
A25: R&D % Revenue - Base | E25: 0.51199043 | F25: 0.51199043 | G25: 0.51199043 | H25: 0.51199043 | I25: 0.51199043
A26: R&D % Revenue - Bull | E26: 0.51199043 | F26: 0.51199043 | G26: 0.51199043 | H26: 0.51199043 | I26: 0.51199043
A27: R&D % Revenue - Bear | E27: 0.51699043 | F27: 0.51699043 | G27: 0.51699043 | H27: 0.51699043 | I27: 0.51699043
A28: R&D % Revenue (Selected) | E28: =OFFSET(E25,$G$2-1,0) | F28: =OFFSET(F25,$G$2-1,0) | G28: =OFFSET(G25,$G$2-1,0) | H28: =OFFSET(H25,$G$2-1,0) | I28: =OFFSET(I25,$G$2-1,0)
A30: D&A % Revenue | E30: 0.10876678 | F30: 0.10876678 | G30: 0.10876678 | H30: 0.10876678 | I30: 0.10876678
A31: CapEx % Revenue | E31: 0.08811803 | F31: 0.08811803 | G31: 0.08811803 | H31: 0.08811803 | I31: 0.08811803
A32: Tax Rate | E32: 0.21 | F32: 0.21 | G32: 0.21 | H32: 0.21 | I32: 0.21
A34: Valuation Assumptions
A35: WACC - Base | C35: 0.0901
A36: WACC - Bull | C36: 0.0801
A37: WACC - Bear | C37: 0.1101
A38: WACC (Selected) | C38: =OFFSET(C35,$G$2-1,0)
A40: Terminal Value Multiple - Base | C40: 21
A41: Terminal Value Multiple - Bull | C41: 23
A42: Terminal Value Multiple - Bear | C42: 18
A43: Terminal Value Multiple (Selected) | C43: =OFFSET(C40,$G$2-1,0)

Sheet Financial Statements
A1: Netskope, Inc. (NTSK) - Historical Financial Statements
A3: ($ in millions) | C3: FY2024 | D3: FY2025
A5: Income Statement
A6: Total Revenue | C6: 406.883 | D6: 538.268
A7: Cost of Revenue | C7: 163.633 | D7: 190.369
A8: Gross Profit | C8: 243.25 | D8: 347.899
A9: Gross Margin | C9: 0.59783771 | D9: 0.64633045
A11: R&D Expense | C11: 224.496 | D11: 254.189
A12: SG&A Expense | C12: 331.552 | D12: 349.451
A13: Operating Income (EBIT) | C13: -312.798 | D13: -255.741
A14: EBIT Margin | C14: -0.76876645 | D14: -0.47511834
A16: Interest Expense | C16: 0 | D16: 0
A17: Tax Provision | C17: 6.784 | D17: 4.243
A18: Net Income | C18: -344.852 | D18: -354.51
A19: Net Margin | C19: -0.84754585 | D19: -0.65861244
... A24: D&A | C24: 49.548 | D24: 51.544
A27: Balance Sheet
A28: Cash & Equivalents | C28: 163.054 | D28: 166.012
A29: Current Assets | C29: 480.131 | D29: 528.405
A30: Net PP&E | C30: 127.445 | D30: 134.051
A31: Goodwill | C31: 57.176 | D31: 61.083
A32: Total Assets | C32: 773.788 | D32: 858.506
A34: Current Liabilities | C34: 427.558 | D34: 526.708
A35: Total Debt | C35: 508.503 | D35: 662.697
A36: Total Liabilities | C36: 1030.608 | D36: 1344.095
A38: Total Equity | C38: -256.82 | D38: -485.589
A41: Cash Flow Statement
A42: Operating Cash Flow | C42: -167.166 | D42: -110.678
A43: Capital Expenditure | C43: -41.152 | D43: -40.422
A44: Free Cash Flow | C44: -208.318 | D44: -151.1
A46: D&A | C46: 49.548 | D46: 51.544
A47: Stock-Based Compensation | C47: 60.991 | D47: 50.834
A48: Change in Working Capital | C48: -5.269 | D48: -10.466

Sheet Model
A1: Netskope, Inc. (NTSK) - Financial Model
A2: Scenario: | C2: =Assumptions!G2
A4: ($M) | C4: FY2024 | D4: FY2025 | E4: FY2026 | F4: FY2027 | G4: FY2028 | H4: FY2029 | I4: FY2030
E5: Proj. | F5: Proj. | G5: Proj. | H5: Proj. | I5: Proj.
A7: Revenue by Segment
A8: Software - Infrastructure | C8: 406.883 | D8: 538.268 | E8: =Assumptions!E12 | F8: =Assumptions!F12 | G8: =Assumptions!G12 | H8: =Assumptions!H12 | I8: =Assumptions!I12
A9: YoY Growth | D9: =IFERROR(D8/C8-1,"-") | E9: =IFERROR(E8/D8-1,"-") | F9: =IFERROR(F8/E8-1,"-") | G9: =IFERROR(G8/F8-1,"-") | H9: =IFERROR(H8/G8-1,"-") | I9: =IFERROR(I8/H8-1,"-")
A11: Total Revenue | C11: =C8 | D11: =D8 | E11: =E8 | F11: =F8 | G11: =G8 | H11: =H8 | I11: =I8
A12: Revenue Growth % | D12: =IFERROR(D11/C11-1,"-") | E12: =IFERROR(E11/D11-1,"-") | F12: =IFERROR(F11/E11-1,"-") | G12: =IFERROR(G11/F11-1,"-") | H12: =IFERROR(H11/G11-1,"-") | I12: =IFERROR(I11/H11-1,"-")
A14: Profit & Loss
A15: Revenue | C15: =C11 | D15: =D11 | E15: =E11 | F15: =F11 | G15: =G11 | H15: =H11 | I15: =I11
A16: Cost of Goods Sold (COGS) | C16: 163.633 | D16: 190.369 | E16: =-E15*(1-Assumptions!E18) | F16: =-F15*(1-Assumptions!F18) | G16: =-G15*(1-Assumptions!G18) | H16: =-H15*(1-Assumptions!H18) | I16: =-I15*(1-Assumptions!I18)
A17: Gross Profit | C17: =C15+C16 | D17: =D15+D16 | E17: =E15+E16 | F17: =F15+F16 | G17: =G15+G16 | H17: =H15+H16 | I17: =I15+I16
A18: Gross Margin % | C18: =IFERROR(C17/C15,"-") | D18: =IFERROR(D17/D15,"-") | E18: =IFERROR(E17/E15,"-") | F18: =IFERROR(F17/F15,"-") | G18: =IFERROR(G17/G15,"-") | H18: =IFERROR(H17/H15,"-") | I18: =IFERROR(I17/I15,"-")
A20: SG&A Expense | C20: 331.552 | D20: 349.451 | E20: =-E15*Assumptions!E24 | F20: =-F15*Assumptions!F24 | G20: =-G15*Assumptions!G24 | H20: =-H15*Assumptions!H24 | I20: =-I15*Assumptions!I24
A21: R&D Expense | C21: 224.496 | D21: 254.189 | E21: =-E15*Assumptions!E30 | F21: =-F15*Assumptions!F30 | G21: =-G15*Assumptions!G30 | H21: =-H15*Assumptions!H30 | I21: =-I15*Assumptions!I30
A22: Depreciation & Amortization | C22: 49.548 | D22: 51.544 | E22: =-E15*Assumptions!E32 | F22: =-F15*Assumptions!F32 | G22: =-G15*Assumptions!G32 | H22: =-H15*Assumptions!H32 | I22: =-I15*Assumptions!I32
A24: EBITDA | C24: =C17+C20+C21 | D24: =D17+D20+D21 | E24: =E17+E20+E21 | F24: =F17+F20+F21 | G24: =G17+G20+G21 | H24: =H17+H20+H21 | I24: =I17+I20+I21
A25: EBITDA Margin % | C25: =IFERROR(C24/C15,"-") | D25: =IFERROR(D24/D15,"-") | E25: =IFERROR(E24/E15,"-") | F25: =IFERROR(F24/F15,"-") | G25: =IFERROR(G24/G15,"-") | H25: =IFERROR(H24/H15,"-") | I25: =IFERROR(I24/I15,"-")
A26: EBIT | C26: =C24+C22 | D26: =D24+D22 | E26: =E24+E22 | F26: =F24+F22 | G26: =G24+G22 | H26: =H24+H22 | I26: =I24+I22
A27: EBIT Margin % | C27: =IFERROR(C26/C15,"-") | D27: =IFERROR(D26/D15,"-") | E27: =IFERROR(E26/E15,"-") | F27: =IFERROR(F26/F15,"-") | G27: =IFERROR(G26/G15,"-") | H27: =IFERROR(H26/H15,"-") | I27: =IFERROR(I26/I15,"-")
A29: Interest Expense | C29: 0 | D29: 0 | E29: 0 | F29: 0 | G29: 0 | H29: 0 | I29: 0
A30: Earnings Before Tax (EBT) | C30: =C26+C29 | D30: =D26+D29 | E30: =E26+E29 | F30: =F26+F29 | G30: =G26+G29 | H30: =H26+H29 | I30: =I26+I29
A31: Taxes | C31: 6.784 | D31: 4.243 | E31: =-ABS(E30)*Assumptions!E34 | F31: =-ABS(F30)*Assumptions!F34 | G31: =-ABS(G30)*Assumptions!G34 | H31: =-ABS(H30)*Assumptions!H34 | I31: =-ABS(I30)*Assumptions!I34
A32: Net Income | C32: =C30+C31 | D32: =D30+D31 | E32: =E30+E31 | F32: =F30+F31 | G32: =G30+G31 | H32: =H30+H31 | I32: =I30+I31
A33: Net Margin % | C33: =IFERROR(C32/C15,"-") | D33: =IFERROR(D32/D15,"-") | E33: =IFERROR(E32/E15,"-") | F33: =IFERROR(F32/F15,"-") | G33: =IFERROR(G32/G15,"-") | H33: =IFERROR(H32/H15,"-") | I33: =IFERROR(I32/I15,"-")
A36: Cash Flow
A37: EBITDA | C37: =C24 | D37: =D24 | E37: =E24 | F37: =F24 | G37: =G24 | H37: =H24 | I37: =I24
A38: (-) Taxes | C38: =C31 | D38: =D31 | E38: =E31 | F38: =F31 | G38: =G31 | H38: =H31 | I38: =I31
A39: (+/-) Change in Working Capital | C39: -5.269 | D39: -10.466 | E39: 0 | F39: 0 | G39: 0 | H39: 0 | I39: 0
A40: Operating Cash Flow | C40: =C37+C38+C39 | D40: =D37+D38+D39 | E40: =E37+E38+E39 | F40: =F37+F38+F39 | G40: =G37+G38+G39 | H40: =H37+H38+H39 | I40: =I37+I38+I39
A42: (-) Capital Expenditure | C42: -41.152 | D42: -40.422 | E42: =-ABS(E15)*Assumptions!E33 | F42: =-ABS(F15)*Assumptions!F33 | G42: =-ABS(G15)*Assumptions!G33 | H42: =-ABS(H15)*Assumptions!H33 | I42: =-ABS(I15)*Assumptions!I33
A43: Unlevered Free Cash Flow (UFCF) | C43: =C40+C42 | D43: =D40+D42 | E43: =E40+E42 | F43: =F40+F42 | G43: =G40+G42 | H43: =H40+H42 | I43: =I40+I42
A200: __REF_EBITDA_ROW | B200: 24
A201: __REF_TAXES_ROW | B201: 31
A202: __REF_CAPEX_ROW | B202: 42
A203: __REF_UFCF_ROW | B203: 43
A204: __REF_WC_ROW | B204: 39
A205: __REF_NI_ROW | B205: 32
A206: __REF_TOTAL_REV_ROW | B206: 11

Sheet Valuation
A1: Netskope, Inc. (NTSK) - DCF Valuation
A2: Scenario: | C2: =Assumptions!G2 | E2: Current Price: | F2: 9.66
A4: Year | E4: 2026 | F4: 2027 | G4: 2028 | H4: 2029 | I4: 2030
A5: Year # | E5: 1 | F5: 2 | G5: 3 | H5: 4 | I5: 5
A7: DCF Inputs (from Model)
A8: EBITDA ($M) | E8: =INDIRECT("Model!"&"E"&Model!B200) | F8: =INDIRECT("Model!"&"F"&Model!B200) | G8: =INDIRECT("Model!"&"G"&Model!B200) | H8: =INDIRECT("Model!"&"H"&Model!B200) | I8: =INDIRECT("Model!"&"I"&Model!B200)
A9: (-) Taxes ($M) | E9: =INDIRECT("Model!"&"E"&Model!B201) | F9: =INDIRECT("Model!"&"F"&Model!B201) | G9: =INDIRECT("Model!"&"G"&Model!B201) | H9: =INDIRECT("Model!"&"H"&Model!B201) | I9: =INDIRECT("Model!"&"I"&Model!B201)
A10: (+/-) Change in WC ($M) | E10: =INDIRECT("Model!"&"E"&Model!B204) | F10: =INDIRECT("Model!"&"F"&Model!B204) | G10: =INDIRECT("Model!"&"G"&Model!B204) | H10: =INDIRECT("Model!"&"H"&Model!B204) | I10: =INDIRECT("Model!"&"I"&Model!B204)
A11: (-) CapEx ($M) | E11: =INDIRECT("Model!"&"E"&Model!B202) | F11: =INDIRECT("Model!"&"F"&Model!B202) | G11: =INDIRECT("Model!"&"G"&Model!B202) | H11: =INDIRECT("Model!"&"H"&Model!B202) | I11: =INDIRECT("Model!"&"I"&Model!B202)
A12: Unlevered Free Cash Flow ($M) | E12: =E8+E9+E10+E11 | F12: =F8+F9+F10+F11 | G12: =G8+G9+G10+G11 | H12: =H8+H9+H10+H11 | I12: =I8+I9+I10+I11
A14: Discounted Cash Flow
A15: WACC | C15: =Assumptions!C42
A16: Terminal Value Multiple | C16: =Assumptions!C48
A18: Discount Factor | E18: =1/(1+$C$15)^1 | F18: =1/(1+$C$15)^2 | G18: =1/(1+$C$15)^3 | H18: =1/(1+$C$15)^4 | I18: =1/(1+$C$15)^5
A19: PV of UFCF ($M) | E19: =E12*E18 | F19: =F12*F18 | G19: =G12*G18 | H19: =H12*H18 | I19: =I12*I18
A21: Terminal Value ($M) | I21: =I12*$C$16
A22: PV of Terminal Value ($M) | I22: =I21*I18
A24: Valuation Summary
A25: Sum of PV of UFCF ($M) | C25: =SUM(E19:I19)
A26: PV of Terminal Value ($M) | C26: =I22
A27: Enterprise Value ($M) | C27: =C25+C26
A29: (-) Net Debt ($M) | C29: -496.685
A30: Equity Value ($M) | C30: =C27+C29
A32: Shares Outstanding (M) | C32: 156
A33: Equity Value per Share ($) | C33: =C30/C32
A34: Upside / Downside vs Current | C34: =C33/9.66-1
A37: Sensitivity Analysis: WACC vs Terminal Value Multiple
A38: WACC \ TV Multiple | C38: 17x | D38: 19x | E38: 21x | F38: 23x | G38: 25x
A39: 0.0601 | C39: =(E$12/(1+$A$39)^1+F$12/(1+$A$39)^2+G$12/(1+$A$39)^3+H$12/(1+$A$39)^4+I$12/(1+$A$39)^5+I$12*17/(1+$A$39)^5+$C$29)/$C$32 | D39: =(E$12/(1+$A$39)^1+F$12/(1+$A$39)^2+G$12/(1+$A$39)^3+H$12/(1+$A$39)^4+I$12/(1+$A$39)^5+I$12*19/(1+$A$39)^5+$C$29)/$C$32 | E39: =(E$12/(1+$A$39)^1+F$12/(1+$A$39)^2+G$12/(1+$A$39)^3+H$12/(1+$A$39)^4+I$12/(1+$A$39)^5+I$12*21/(1+$A$39)^5+$C$29)/$C$32 | F39: =(E$12/(1+$A$39)^1+F$12/(1+$A$39)^2+G$12/(1+$A$39)^3+H$12/(1+$A$39)^4+I$12/(1+$A$39)^5+I$12*23/(1+$A$39)^5+$C$29)/$C$32 | G39: =(E$12/(1+$A$39)^1+F$12/(1+$A$39)^2+G$12/(1+$A$39)^3+H$12/(1+$A$39)^4+I$12/(1+$A$39)^5+I$12*25/(1+$A$39)^5+$C$29)/$C$32
A40: 0.0701 | C40: =(E$12/(1+$A$40)^1+F$12/(1+$A$40)^2+G$12/(1+$A$40)^3+H$12/(1+$A$40)^4+I$12/(1+$A$40)^5+I$12*17/(1+$A$40)^5+$C$29)/$C$32 | D40: =(E$12/(1+$A$40)^1+F$12/(1+$A$40)^2+G$12/(1+$A$40)^3+H$12/(1+$A$40)^4+I$12/(1+$A$40)^5+I$12*19/(1+$A$40)^5+$C$29)/$C$32 | E40: =(E$12/(1+$A$40)^1+F$12/(1+$A$40)^2+G$12/(1+$A$40)^3+H$12/(1+$A$40)^4+I$12/(1+$A$40)^5+I$12*21/(1+$A$40)^5+$C$29)/$C$32 | F40: =(E$12/(1+$A$40)^1+F$12/(1+$A$40)^2+G$12/(1+$A$40)^3+H$12/(1+$A$40)^4+I$12/(1+$A$40)^5+I$12*23/(1+$A$40)^5+$C$29)/$C$32 | G40: =(E$12/(1+$A$40)^1+F$12/(1+$A$40)^2+G$12/(1+$A$40)^3+H$12/(1+$A$40)^4+I$12/(1+$A$40)^5+I$12*25/(1+$A$40)^5+$C$29)/$C$32
A41: 0.0801 | C41: =(E$12/(1+$A$41)^1+F$12/(1+$A$41)^2+G$12/(1+$A$41)^3+H$12/(1+$A$41)^4+I$12/(1+$A$41)^5+I$12*17/(1+$A$41)^5+$C$29)/$C$32 | D41: =(E$12/(1+$A$41)^1+F$12/(1+$A$41)^2+G$12/(1+$A$41)^3+H$12/(1+$A$41)^4+I$12/(1+$A$41)^5+I$12*19/(1+$A$41)^5+$C$29)/$C$32 | E41: =(E$12/(1+$A$41)^1+F$12/(1+$A$41)^2+G$12/(1+$A$41)^3+H$12/(1+$A$41)^4+I$12/(1+$A$41)^5+I$12*21/(1+$A$41)^5+$C$29)/$C$32 | F41: =(E$12/(1+$A$41)^1+F$12/(1+$A$41)^2+G$12/(1+$A$41)^3+H$12/(1+$A$41)^4+I$12/(1+$A$41)^5+I$12*23/(1+$A$41)^5+$C$29)/$C$32 | G41: =(E$12/(1+$A$41)^1+F$12/(1+$A$41)^2+G$12/(1+$A$41)^3+H$12/(1+$A$41)^4+I$12/(1+$A$41)^5+I$12*25/(1+$A$41)^5+$C$29)/$C$32
A42: 0.0901 | C42: =(E$12/(1+$A$42)^1+F$12/(1+$A$42)^2+G$12/(1+$A$42)^3+H$12/(1+$A$42)^4+I$12/(1+$A$42)^5+I$12*17/(1+$A$42)^5+$C$29)/$C$32 | D42: =(E$12/(1+$A$42)^1+F$12/(1+$A$42)^2+G$12/(1+$A$42)^3+H$12/(1+$A$42)^4+I$12/(1+$A$42)^5+I$12*19/(1+$A$42)^5+$C$29)/$C$32 | E42: =(E$12/(1+$A$42)^1+F$12/(1+$A$42)^2+G$12/(1+$A$42)^3+H$12/(1+$A$42)^4+I$12/(1+$A$42)^5+I$12*21/(1+$A$42)^5+$C$29)/$C$32 | F42: =(E$12/(1+$A$42)^1+F$12/(1+$A$42)^2+G$12/(1+$A$42)^3+H$12/(1+$A$42)^4+I$12/(1+$A$42)^5+I$12*23/(1+$A$42)^5+$C$29)/$C$32 | G42: =(E$12/(1+$A$42)^1+F$12/(1+$A$42)^2+G$12/(1+$A$42)^3+H$12/(1+$A$42)^4+I$12/(1+$A$42)^5+I$12*25/(1+$A$42)^5+$C$29)/$C$32
A43: 0.1001 | C43: =(E$12/(1+$A$43)^1+F$12/(1+$A$43)^2+G$12/(1+$A$43)^3+H$12/(1+$A$43)^4+I$12/(1+$A$43)^5+I$12*17/(1+$A$43)^5+$C$29)/$C$32 | D43: =(E$12/(1+$A$43)^1+F$12/(1+$A$43)^2+G$12/(1+$A$43)^3+H$12/(1+$A$43)^4+I$12/(1+$A$43)^5+I$12*19/(1+$A$43)^5+$C$29)/$C$32 | E43: =(E$12/(1+$A$43)^1+F$12/(1+$A$43)^2+G$12/(1+$A$43)^3+H$12/(1+$A$43)^4+I$12/(1+$A$43)^5+I$12*21/(1+$A$43)^5+$C$29)/$C$32 | F43: =(E$12/(1+$A$43)^1+F$12/(1+$A$43)^2+G$12/(1+$A$43)^3+H$12/(1+$A$43)^4+I$12/(1+$A$43)^5+I$12*23/(1+$A$43)^5+$C$29)/$C$32 | G43: =(E$12/(1+$A$43)^1+F$12/(1+$A$43)^2+G$12/(1+$A$43)^3+H$12/(1+$A$43)^4+I$12/(1+$A$43)^5+I$12*25/(1+$A$43)^5+$C$29)/$C$32
A44: 0.1101 | C44: =(E$12/(1+$A$44)^1+F$12/(1+$A$44)^2+G$12/(1+$A$44)^3+H$12/(1+$A$44)^4+I$12/(1+$A$44)^5+I$12*17/(1+$A$44)^5+$C$29)/$C$32 | D44: =(E$12/(1+$A$44)^1+F$12/(1+$A$44)^2+G$12/(1+$A$44)^3+H$12/(1+$A$44)^4+I$12/(1+$A$44)^5+I$12*19/(1+$A$44)^5+$C$29)/$C$32 | E44: =(E$12/(1+$A$44)^1+F$12/(1+$A$44)^2+G$12/(1+$A$44)^3+H$12/(1+$A$44)^4+I$12/(1+$A$44)^5+I$12*21/(1+$A$44)^5+$C$29)/$C$32 | F44: =(E$12/(1+$A$44)^1+F$12/(1+$A$44)^2+G$12/(1+$A$44)^3+H$12/(1+$A$44)^4+I$12/(1+$A$44)^5+I$12*23/(1+$A$44)^5+$C$29)/$C$32 | G44: =(E$12/(1+$A$44)^1+F$12/(1+$A$44)^2+G$12/(1+$A$44)^3+H$12/(1+$A$44)^4+I$12/(1+$A$44)^5+I$12*25/(1+$A$44)^5+$C$29)/$C$32
A45: 0.1201 | C45: =(E$12/(1+$A$45)^1+F$12/(1+$A$45)^2+G$12/(1+$A$45)^3+H$12/(1+$A$45)^4+I$12/(1+$A$45)^5+I$12*17/(1+$A$45)^5+$C$29)/$C$32 | D45: =(E$12/(1+$A$45)^1+F$12/(1+$A$45)^2+G$12/(1+$A$45)^3+H$12/(1+$A$45)^4+I$12/(1+$A$45)^5+I$12*19/(1+$A$45)^5+$C$29)/$C$32 | E45: =(E$12/(1+$A$45)^1+F$12/(1+$A$45)^2+G$12/(1+$A$45)^3+H$12/(1+$A$45)^4+I$12/(1+$A$45)^5+I$12*21/(1+$A$45)^5+$C$29)/$C$32 | F45: =(E$12/(1+$A$45)^1+F$12/(1+$A$45)^2+G$12/(1+$A$45)^3+H$12/(1+$A$45)^4+I$12/(1+$A$45)^5+I$12*23/(1+$A$45)^5+$C$29)/$C$32 | G45: =(E$12/(1+$A$45)^1+F$12/(1+$A$45)^2+G$12/(1+$A$45)^3+H$12/(1+$A$45)^4+I$12/(1+$A$45)^5+I$12*25/(1+$A$45)^5+$C$29)/$C$32
