Workbook

Sheet Assumptions
A1: None (ITX) - Assumptions
A2: Scenario Selector: | G2: 1 | H2: 1=Base, 2=Bull, 3=Bear
C4: FY2025 | D4: FY2026 | E4: FY2027 | F4: FY2028 | G4: FY2029
A6: Principal
A7: Revenue ($M)
A8: Revenue Growth - Base | C8: 0.05 | D8: 0.045 | E8: 0.04 | F8: 0.035 | G8: 0.03
A9: Revenue Growth - Bull | C9: 0.08 | D9: 0.072 | E9: 0.064 | F9: 0.056 | G9: 0.048
A10: Revenue Growth - Bear | C10: 0.02 | D10: 0.018 | E10: 0.016 | F10: 0.014 | G10: 0.012
A11: Revenue Growth (Selected) | C11: =OFFSET(C8,$G$2-1,0) | D11: =OFFSET(D8,$G$2-1,0) | E11: =OFFSET(E8,$G$2-1,0) | F11: =OFFSET(F8,$G$2-1,0) | G11: =OFFSET(G8,$G$2-1,0)
A12: Revenue Projected ($M) | C12: =B7*(1+C11) | D12: =C12*(1+D11) | E12: =D12*(1+E11) | F12: =E12*(1+F11) | G12: =F12*(1+G11)
A14: Operating Assumptions
A15: Gross Margin - Base | C15: 0.4 | D15: 0.4 | E15: 0.4 | F15: 0.4 | G15: 0.4
A16: Gross Margin - Bull | C16: 0.42 | D16: 0.42 | E16: 0.42 | F16: 0.42 | G16: 0.42
A17: Gross Margin - Bear | C17: 0.38 | D17: 0.38 | E17: 0.38 | F17: 0.38 | G17: 0.38
A18: Gross Margin (Selected) | C18: =OFFSET(C15,$G$2-1,0) | D18: =OFFSET(D15,$G$2-1,0) | E18: =OFFSET(E15,$G$2-1,0) | F18: =OFFSET(F15,$G$2-1,0) | G18: =OFFSET(G15,$G$2-1,0)
A20: SG&A % Revenue - Base | C20: 0.15 | D20: 0.15 | E20: 0.15 | F20: 0.15 | G20: 0.15
A21: SG&A % Revenue - Bull | C21: 0.14 | D21: 0.14 | E21: 0.14 | F21: 0.14 | G21: 0.14
A22: SG&A % Revenue - Bear | C22: 0.16 | D22: 0.16 | E22: 0.16 | F22: 0.16 | G22: 0.16
A23: SG&A % Revenue (Selected) | C23: =OFFSET(C20,$G$2-1,0) | D23: =OFFSET(D20,$G$2-1,0) | E23: =OFFSET(E20,$G$2-1,0) | F23: =OFFSET(F20,$G$2-1,0) | G23: =OFFSET(G20,$G$2-1,0)
A25: R&D % Revenue - Base | C25: 0.05 | D25: 0.05 | E25: 0.05 | F25: 0.05 | G25: 0.05
A26: R&D % Revenue - Bull | C26: 0.05 | D26: 0.05 | E26: 0.05 | F26: 0.05 | G26: 0.05
A27: R&D % Revenue - Bear | C27: 0.055 | D27: 0.055 | E27: 0.055 | F27: 0.055 | G27: 0.055
A28: R&D % Revenue (Selected) | C28: =OFFSET(C25,$G$2-1,0) | D28: =OFFSET(D25,$G$2-1,0) | E28: =OFFSET(E25,$G$2-1,0) | F28: =OFFSET(F25,$G$2-1,0) | G28: =OFFSET(G25,$G$2-1,0)
A30: D&A % Revenue | C30: 0.03 | D30: 0.03 | E30: 0.03 | F30: 0.03 | G30: 0.03
A31: CapEx % Revenue | C31: 0.04 | D31: 0.04 | E31: 0.04 | F31: 0.04 | G31: 0.04
A32: Tax Rate | C32: 0.21 | D32: 0.21 | E32: 0.21 | F32: 0.21 | G32: 0.21
A34: Valuation Assumptions
A35: WACC - Base | C35: 0.0879
A36: WACC - Bull | C36: 0.0779
A37: WACC - Bear | C37: 0.1079
A38: WACC (Selected) | C38: =OFFSET(C35,$G$2-1,0)
A40: Terminal Value Multiple - Base | C40: 12
A41: Terminal Value Multiple - Bull | C41: 14
A42: Terminal Value Multiple - Bear | C42: 9
A43: Terminal Value Multiple (Selected) | C43: =OFFSET(C40,$G$2-1,0)

Sheet Financial Statements
A1: None (ITX) - Historical Financial Statements
A3: ($ in millions)
A5: Income Statement
A6: Total Revenue
A7: Cost of Revenue
A8: Gross Profit
A9: Gross Margin
A11: R&D Expense
A12: SG&A Expense
A13: Operating Income (EBIT)
A14: EBIT Margin
A16: Interest Expense
... A48: Change in Working Capital

Sheet Model
A1: None (ITX) - Financial Model
A2: Scenario: | C2: =Assumptions!G2
A4: ($M) | C4: FY2025 | D4: FY2026 | E4: FY2027 | F4: FY2028 | G4: FY2029
C5: Proj. | D5: Proj. | E5: Proj. | F5: Proj. | G5: Proj.
A7: Revenue by Segment
A8: Principal | C8: =Assumptions!C12 | D8: =Assumptions!D12 | E8: =Assumptions!E12 | F8: =Assumptions!F12 | G8: =Assumptions!G12
A9: YoY Growth | D9: =IFERROR(D8/C8-1,"-") | E9: =IFERROR(E8/D8-1,"-") | F9: =IFERROR(F8/E8-1,"-") | G9: =IFERROR(G8/F8-1,"-")
A11: Total Revenue | C11: =C8 | D11: =D8 | E11: =E8 | F11: =F8 | G11: =G8
A12: Revenue Growth % | D12: =IFERROR(D11/C11-1,"-") | E12: =IFERROR(E11/D11-1,"-") | F12: =IFERROR(F11/E11-1,"-") | G12: =IFERROR(G11/F11-1,"-")
A14: Profit & Loss
A15: Revenue | C15: =C11 | D15: =D11 | E15: =E11 | F15: =F11 | G15: =G11
A16: Cost of Goods Sold (COGS) | C16: =-C15*(1-Assumptions!C18) | D16: =-D15*(1-Assumptions!D18) | E16: =-E15*(1-Assumptions!E18) | F16: =-F15*(1-Assumptions!F18) | G16: =-G15*(1-Assumptions!G18)
A17: Gross Profit | C17: =C15+C16 | D17: =D15+D16 | E17: =E15+E16 | F17: =F15+F16 | G17: =G15+G16
A18: Gross Margin % | C18: =IFERROR(C17/C15,"-") | D18: =IFERROR(D17/D15,"-") | E18: =IFERROR(E17/E15,"-") | F18: =IFERROR(F17/F15,"-") | G18: =IFERROR(G17/G15,"-")
A20: SG&A Expense | C20: =-C15*Assumptions!C24 | D20: =-D15*Assumptions!D24 | E20: =-E15*Assumptions!E24 | F20: =-F15*Assumptions!F24 | G20: =-G15*Assumptions!G24
A21: R&D Expense | C21: =-C15*Assumptions!C30 | D21: =-D15*Assumptions!D30 | E21: =-E15*Assumptions!E30 | F21: =-F15*Assumptions!F30 | G21: =-G15*Assumptions!G30
A22: Depreciation & Amortization | C22: =-C15*Assumptions!C32 | D22: =-D15*Assumptions!D32 | E22: =-E15*Assumptions!E32 | F22: =-F15*Assumptions!F32 | G22: =-G15*Assumptions!G32
A24: EBITDA | C24: =C17+C20+C21 | D24: =D17+D20+D21 | E24: =E17+E20+E21 | F24: =F17+F20+F21 | G24: =G17+G20+G21
A25: EBITDA Margin % | C25: =IFERROR(C24/C15,"-") | D25: =IFERROR(D24/D15,"-") | E25: =IFERROR(E24/E15,"-") | F25: =IFERROR(F24/F15,"-") | G25: =IFERROR(G24/G15,"-")
A26: EBIT | C26: =C24+C22 | D26: =D24+D22 | E26: =E24+E22 | F26: =F24+F22 | G26: =G24+G22
A27: EBIT Margin % | C27: =IFERROR(C26/C15,"-") | D27: =IFERROR(D26/D15,"-") | E27: =IFERROR(E26/E15,"-") | F27: =IFERROR(F26/F15,"-") | G27: =IFERROR(G26/G15,"-")
A29: Interest Expense
A30: Earnings Before Tax (EBT) | C30: =C26+C29 | D30: =D26+D29 | E30: =E26+E29 | F30: =F26+F29 | G30: =G26+G29
A31: Taxes | C31: =-ABS(C30)*Assumptions!C34 | D31: =-ABS(D30)*Assumptions!D34 | E31: =-ABS(E30)*Assumptions!E34 | F31: =-ABS(F30)*Assumptions!F34 | G31: =-ABS(G30)*Assumptions!G34
A32: Net Income | C32: =C30+C31 | D32: =D30+D31 | E32: =E30+E31 | F32: =F30+F31 | G32: =G30+G31
A33: Net Margin % | C33: =IFERROR(C32/C15,"-") | D33: =IFERROR(D32/D15,"-") | E33: =IFERROR(E32/E15,"-") | F33: =IFERROR(F32/F15,"-") | G33: =IFERROR(G32/G15,"-")
A36: Cash Flow
A37: EBITDA | C37: =C24 | D37: =D24 | E37: =E24 | F37: =F24 | G37: =G24
A38: (-) Taxes | C38: =C31 | D38: =D31 | E38: =E31 | F38: =F31 | G38: =G31
A39: (+/-) Change in Working Capital | C39: 0 | D39: 0 | E39: 0 | F39: 0 | G39: 0
A40: Operating Cash Flow | C40: =C37+C38+C39 | D40: =D37+D38+D39 | E40: =E37+E38+E39 | F40: =F37+F38+F39 | G40: =G37+G38+G39
A42: (-) Capital Expenditure | C42: =-ABS(C15)*Assumptions!C33 | D42: =-ABS(D15)*Assumptions!D33 | E42: =-ABS(E15)*Assumptions!E33 | F42: =-ABS(F15)*Assumptions!F33 | G42: =-ABS(G15)*Assumptions!G33
A43: Unlevered Free Cash Flow (UFCF) | C43: =C40+C42 | D43: =D40+D42 | E43: =E40+E42 | F43: =F40+F42 | G43: =G40+G42
A200: __REF_EBITDA_ROW | B200: 24
A201: __REF_TAXES_ROW | B201: 31
A202: __REF_CAPEX_ROW | B202: 42
A203: __REF_UFCF_ROW | B203: 43
A204: __REF_WC_ROW | B204: 39
A205: __REF_NI_ROW | B205: 32
A206: __REF_TOTAL_REV_ROW | B206: 11

Sheet Valuation
A1: None (ITX) - DCF Valuation
A2: Scenario: | C2: =Assumptions!G2 | E2: Current Price: | F2: 0
A4: Year | C4: 2025 | D4: 2026 | E4: 2027 | F4: 2028 | G4: 2029
A5: Year # | C5: 1 | D5: 2 | E5: 3 | F5: 4 | G5: 5
A7: DCF Inputs (from Model)
A8: EBITDA ($M) | C8: =INDIRECT("Model!"&"C"&Model!B200) | D8: =INDIRECT("Model!"&"D"&Model!B200) | E8: =INDIRECT("Model!"&"E"&Model!B200) | F8: =INDIRECT("Model!"&"F"&Model!B200) | G8: =INDIRECT("Model!"&"G"&Model!B200)
A9: (-) Taxes ($M) | C9: =INDIRECT("Model!"&"C"&Model!B201) | D9: =INDIRECT("Model!"&"D"&Model!B201) | E9: =INDIRECT("Model!"&"E"&Model!B201) | F9: =INDIRECT("Model!"&"F"&Model!B201) | G9: =INDIRECT("Model!"&"G"&Model!B201)
A10: (+/-) Change in WC ($M) | C10: =INDIRECT("Model!"&"C"&Model!B204) | D10: =INDIRECT("Model!"&"D"&Model!B204) | E10: =INDIRECT("Model!"&"E"&Model!B204) | F10: =INDIRECT("Model!"&"F"&Model!B204) | G10: =INDIRECT("Model!"&"G"&Model!B204)
A11: (-) CapEx ($M) | C11: =INDIRECT("Model!"&"C"&Model!B202) | D11: =INDIRECT("Model!"&"D"&Model!B202) | E11: =INDIRECT("Model!"&"E"&Model!B202) | F11: =INDIRECT("Model!"&"F"&Model!B202) | G11: =INDIRECT("Model!"&"G"&Model!B202)
A12: Unlevered Free Cash Flow ($M) | C12: =C8+C9+C10+C11 | D12: =D8+D9+D10+D11 | E12: =E8+E9+E10+E11 | F12: =F8+F9+F10+F11 | G12: =G8+G9+G10+G11
A14: Discounted Cash Flow
A15: WACC | C15: =Assumptions!C42
A16: Terminal Value Multiple | C16: =Assumptions!C48
A18: Discount Factor | C18: =1/(1+$C$15)^1 | D18: =1/(1+$C$15)^2 | E18: =1/(1+$C$15)^3 | F18: =1/(1+$C$15)^4 | G18: =1/(1+$C$15)^5
A19: PV of UFCF ($M) | C19: =C12*C18 | D19: =D12*D18 | E19: =E12*E18 | F19: =F12*F18 | G19: =G12*G18
A21: Terminal Value ($M) | G21: =G12*$C$16
A22: PV of Terminal Value ($M) | G22: =G21*G18
A24: Valuation Summary
A25: Sum of PV of UFCF ($M) | C25: =SUM(C19:G19)
A26: PV of Terminal Value ($M) | C26: =G22
A27: Enterprise Value ($M) | C27: =C25+C26
A29: (-) Net Debt ($M) | C29: 0
A30: Equity Value ($M) | C30: =C27+C29
A32: Shares Outstanding (M) | C32: 0
A33: Equity Value per Share ($) | C33: =C30/C32
A34: Upside / Downside vs Current | C34: =C33/0-1
A37: Sensitivity Analysis: WACC vs Terminal Value Multiple
A38: WACC \ TV Multiple | C38: 8x | D38: 10x | E38: 12x | F38: 14x | G38: 16x
A39: 0.0579 | C39: =(C$12/(1+$A$39)^1+D$12/(1+$A$39)^2+E$12/(1+$A$39)^3+F$12/(1+$A$39)^4+G$12/(1+$A$39)^5+G$12*8/(1+$A$39)^5+$C$29)/$C$32 | D39: =(C$12/(1+$A$39)^1+D$12/(1+$A$39)^2+E$12/(1+$A$39)^3+F$12/(1+$A$39)^4+G$12/(1+$A$39)^5+G$12*10/(1+$A$39)^5+$C$29)/$C$32 | E39: =(C$12/(1+$A$39)^1+D$12/(1+$A$39)^2+E$12/(1+$A$39)^3+F$12/(1+$A$39)^4+G$12/(1+$A$39)^5+G$12*12/(1+$A$39)^5+$C$29)/$C$32 | F39: =(C$12/(1+$A$39)^1+D$12/(1+$A$39)^2+E$12/(1+$A$39)^3+F$12/(1+$A$39)^4+G$12/(1+$A$39)^5+G$12*14/(1+$A$39)^5+$C$29)/$C$32 | G39: =(C$12/(1+$A$39)^1+D$12/(1+$A$39)^2+E$12/(1+$A$39)^3+F$12/(1+$A$39)^4+G$12/(1+$A$39)^5+G$12*16/(1+$A$39)^5+$C$29)/$C$32
A40: 0.0679 | C40: =(C$12/(1+$A$40)^1+D$12/(1+$A$40)^2+E$12/(1+$A$40)^3+F$12/(1+$A$40)^4+G$12/(1+$A$40)^5+G$12*8/(1+$A$40)^5+$C$29)/$C$32 | D40: =(C$12/(1+$A$40)^1+D$12/(1+$A$40)^2+E$12/(1+$A$40)^3+F$12/(1+$A$40)^4+G$12/(1+$A$40)^5+G$12*10/(1+$A$40)^5+$C$29)/$C$32 | E40: =(C$12/(1+$A$40)^1+D$12/(1+$A$40)^2+E$12/(1+$A$40)^3+F$12/(1+$A$40)^4+G$12/(1+$A$40)^5+G$12*12/(1+$A$40)^5+$C$29)/$C$32 | F40: =(C$12/(1+$A$40)^1+D$12/(1+$A$40)^2+E$12/(1+$A$40)^3+F$12/(1+$A$40)^4+G$12/(1+$A$40)^5+G$12*14/(1+$A$40)^5+$C$29)/$C$32 | G40: =(C$12/(1+$A$40)^1+D$12/(1+$A$40)^2+E$12/(1+$A$40)^3+F$12/(1+$A$40)^4+G$12/(1+$A$40)^5+G$12*16/(1+$A$40)^5+$C$29)/$C$32
A41: 0.0779 | C41: =(C$12/(1+$A$41)^1+D$12/(1+$A$41)^2+E$12/(1+$A$41)^3+F$12/(1+$A$41)^4+G$12/(1+$A$41)^5+G$12*8/(1+$A$41)^5+$C$29)/$C$32 | D41: =(C$12/(1+$A$41)^1+D$12/(1+$A$41)^2+E$12/(1+$A$41)^3+F$12/(1+$A$41)^4+G$12/(1+$A$41)^5+G$12*10/(1+$A$41)^5+$C$29)/$C$32 | E41: =(C$12/(1+$A$41)^1+D$12/(1+$A$41)^2+E$12/(1+$A$41)^3+F$12/(1+$A$41)^4+G$12/(1+$A$41)^5+G$12*12/(1+$A$41)^5+$C$29)/$C$32 | F41: =(C$12/(1+$A$41)^1+D$12/(1+$A$41)^2+E$12/(1+$A$41)^3+F$12/(1+$A$41)^4+G$12/(1+$A$41)^5+G$12*14/(1+$A$41)^5+$C$29)/$C$32 | G41: =(C$12/(1+$A$41)^1+D$12/(1+$A$41)^2+E$12/(1+$A$41)^3+F$12/(1+$A$41)^4+G$12/(1+$A$41)^5+G$12*16/(1+$A$41)^5+$C$29)/$C$32
A42: 0.0879 | C42: =(C$12/(1+$A$42)^1+D$12/(1+$A$42)^2+E$12/(1+$A$42)^3+F$12/(1+$A$42)^4+G$12/(1+$A$42)^5+G$12*8/(1+$A$42)^5+$C$29)/$C$32 | D42: =(C$12/(1+$A$42)^1+D$12/(1+$A$42)^2+E$12/(1+$A$42)^3+F$12/(1+$A$42)^4+G$12/(1+$A$42)^5+G$12*10/(1+$A$42)^5+$C$29)/$C$32 | E42: =(C$12/(1+$A$42)^1+D$12/(1+$A$42)^2+E$12/(1+$A$42)^3+F$12/(1+$A$42)^4+G$12/(1+$A$42)^5+G$12*12/(1+$A$42)^5+$C$29)/$C$32 | F42: =(C$12/(1+$A$42)^1+D$12/(1+$A$42)^2+E$12/(1+$A$42)^3+F$12/(1+$A$42)^4+G$12/(1+$A$42)^5+G$12*14/(1+$A$42)^5+$C$29)/$C$32 | G42: =(C$12/(1+$A$42)^1+D$12/(1+$A$42)^2+E$12/(1+$A$42)^3+F$12/(1+$A$42)^4+G$12/(1+$A$42)^5+G$12*16/(1+$A$42)^5+$C$29)/$C$32
A43: 0.0979 | C43: =(C$12/(1+$A$43)^1+D$12/(1+$A$43)^2+E$12/(1+$A$43)^3+F$12/(1+$A$43)^4+G$12/(1+$A$43)^5+G$12*8/(1+$A$43)^5+$C$29)/$C$32 | D43: =(C$12/(1+$A$43)^1+D$12/(1+$A$43)^2+E$12/(1+$A$43)^3+F$12/(1+$A$43)^4+G$12/(1+$A$43)^5+G$12*10/(1+$A$43)^5+$C$29)/$C$32 | E43: =(C$12/(1+$A$43)^1+D$12/(1+$A$43)^2+E$12/(1+$A$43)^3+F$12/(1+$A$43)^4+G$12/(1+$A$43)^5+G$12*12/(1+$A$43)^5+$C$29)/$C$32 | F43: =(C$12/(1+$A$43)^1+D$12/(1+$A$43)^2+E$12/(1+$A$43)^3+F$12/(1+$A$43)^4+G$12/(1+$A$43)^5+G$12*14/(1+$A$43)^5+$C$29)/$C$32 | G43: =(C$12/(1+$A$43)^1+D$12/(1+$A$43)^2+E$12/(1+$A$43)^3+F$12/(1+$A$43)^4+G$12/(1+$A$43)^5+G$12*16/(1+$A$43)^5+$C$29)/$C$32
A44: 0.1079 | C44: =(C$12/(1+$A$44)^1+D$12/(1+$A$44)^2+E$12/(1+$A$44)^3+F$12/(1+$A$44)^4+G$12/(1+$A$44)^5+G$12*8/(1+$A$44)^5+$C$29)/$C$32 | D44: =(C$12/(1+$A$44)^1+D$12/(1+$A$44)^2+E$12/(1+$A$44)^3+F$12/(1+$A$44)^4+G$12/(1+$A$44)^5+G$12*10/(1+$A$44)^5+$C$29)/$C$32 | E44: =(C$12/(1+$A$44)^1+D$12/(1+$A$44)^2+E$12/(1+$A$44)^3+F$12/(1+$A$44)^4+G$12/(1+$A$44)^5+G$12*12/(1+$A$44)^5+$C$29)/$C$32 | F44: =(C$12/(1+$A$44)^1+D$12/(1+$A$44)^2+E$12/(1+$A$44)^3+F$12/(1+$A$44)^4+G$12/(1+$A$44)^5+G$12*14/(1+$A$44)^5+$C$29)/$C$32 | G44: =(C$12/(1+$A$44)^1+D$12/(1+$A$44)^2+E$12/(1+$A$44)^3+F$12/(1+$A$44)^4+G$12/(1+$A$44)^5+G$12*16/(1+$A$44)^5+$C$29)/$C$32
A45: 0.1179 | C45: =(C$12/(1+$A$45)^1+D$12/(1+$A$45)^2+E$12/(1+$A$45)^3+F$12/(1+$A$45)^4+G$12/(1+$A$45)^5+G$12*8/(1+$A$45)^5+$C$29)/$C$32 | D45: =(C$12/(1+$A$45)^1+D$12/(1+$A$45)^2+E$12/(1+$A$45)^3+F$12/(1+$A$45)^4+G$12/(1+$A$45)^5+G$12*10/(1+$A$45)^5+$C$29)/$C$32 | E45: =(C$12/(1+$A$45)^1+D$12/(1+$A$45)^2+E$12/(1+$A$45)^3+F$12/(1+$A$45)^4+G$12/(1+$A$45)^5+G$12*12/(1+$A$45)^5+$C$29)/$C$32 | F45: =(C$12/(1+$A$45)^1+D$12/(1+$A$45)^2+E$12/(1+$A$45)^3+F$12/(1+$A$45)^4+G$12/(1+$A$45)^5+G$12*14/(1+$A$45)^5+$C$29)/$C$32 | G45: =(C$12/(1+$A$45)^1+D$12/(1+$A$45)^2+E$12/(1+$A$45)^3+F$12/(1+$A$45)^4+G$12/(1+$A$45)^5+G$12*16/(1+$A$45)^5+$C$29)/$C$32
