Workbook

Sheet Assumptions
A1: Whitecap Resources Inc. (WCP.TO) - Assumptions
A2: Scenario Selector: | G2: 1 | H2: 1=Base, 2=Bull, 3=Bear
C4: FY2022 | D4: FY2023 | E4: FY2024 | F4: FY2025 | G4: FY2026 | H4: FY2027 | I4: FY2028 | J4: FY2029 | K4: FY2030
A6: Oil & Gas E&P
A7: Revenue ($M) | C7: 4780.4 | D7: 3848.9 | E7: 3937.9 | F7: 5908.8
A8: Revenue Growth - Base | G8: -0.065867341 | H8: -0.045867341 | I8: -0.025867341 | J8: -0.0058673405 | K8: 0.014132659
A9: Revenue Growth - Bull | G9: -0.050867341 | H9: -0.030867341 | I9: -0.010867341 | J9: 0.0091326595 | K9: 0.029132659
A10: Revenue Growth - Bear | G10: -0.080867341 | H10: -0.060867341 | I10: -0.040867341 | J10: -0.020867341 | K10: -0.00086734052
A11: Revenue Growth (Selected) | G11: =OFFSET(G8,$G$2-1,0) | H11: =OFFSET(H8,$G$2-1,0) | I11: =OFFSET(I8,$G$2-1,0) | J11: =OFFSET(J8,$G$2-1,0) | K11: =OFFSET(K8,$G$2-1,0)
A12: Revenue Projected ($M) | G12: =F7*(1+G11) | H12: =G12*(1+H11) | I12: =H12*(1+I11) | J12: =I12*(1+J11) | K12: =J12*(1+K11)
A14: Operating Assumptions
A15: Gross Margin - Base | G15: 0.6127553 | H15: 0.6127553 | I15: 0.6127553 | J15: 0.6127553 | K15: 0.6127553
A16: Gross Margin - Bull | G16: 0.6227553 | H16: 0.6227553 | I16: 0.6227553 | J16: 0.6227553 | K16: 0.6227553
A17: Gross Margin - Bear | G17: 0.6027553 | H17: 0.6027553 | I17: 0.6027553 | J17: 0.6027553 | K17: 0.6027553
A18: Gross Margin (Selected) | G18: =OFFSET(G15,$G$2-1,0) | H18: =OFFSET(H15,$G$2-1,0) | I18: =OFFSET(I15,$G$2-1,0) | J18: =OFFSET(J15,$G$2-1,0) | K18: =OFFSET(K15,$G$2-1,0)
A20: SG&A % Revenue - Base | G20: 0.085749785 | H20: 0.085749785 | I20: 0.085749785 | J20: 0.085749785 | K20: 0.085749785
A21: SG&A % Revenue - Bull | G21: 0.080749785 | H21: 0.080749785 | I21: 0.080749785 | J21: 0.080749785 | K21: 0.080749785
A22: SG&A % Revenue - Bear | G22: 0.090749785 | H22: 0.090749785 | I22: 0.090749785 | J22: 0.090749785 | K22: 0.090749785
A23: SG&A % Revenue (Selected) | G23: =OFFSET(G20,$G$2-1,0) | H23: =OFFSET(H20,$G$2-1,0) | I23: =OFFSET(I20,$G$2-1,0) | J23: =OFFSET(J20,$G$2-1,0) | K23: =OFFSET(K20,$G$2-1,0)
A25: R&D % Revenue - Base | G25: 0 | H25: 0 | I25: 0 | J25: 0 | K25: 0
A26: R&D % Revenue - Bull | G26: 0 | H26: 0 | I26: 0 | J26: 0 | K26: 0
A27: R&D % Revenue - Bear | G27: 0 | H27: 0 | I27: 0 | J27: 0 | K27: 0
A28: R&D % Revenue (Selected) | G28: =OFFSET(G25,$G$2-1,0) | H28: =OFFSET(H25,$G$2-1,0) | I28: =OFFSET(I25,$G$2-1,0) | J28: =OFFSET(J25,$G$2-1,0) | K28: =OFFSET(K25,$G$2-1,0)
A30: D&A % Revenue | G30: 0.23260658 | H30: 0.23260658 | I30: 0.23260658 | J30: 0.23260658 | K30: 0.23260658
A31: CapEx % Revenue | G31: 0.29046086 | H31: 0.29046086 | I31: 0.29046086 | J31: 0.29046086 | K31: 0.29046086
A32: Tax Rate | G32: 0.28790278 | H32: 0.28790278 | I32: 0.28790278 | J32: 0.28790278 | K32: 0.28790278
A34: Valuation Assumptions
A35: WACC - Base | C35: 0.0799
A36: WACC - Bull | C36: 0.0699
A37: WACC - Bear | C37: 0.0899
A38: WACC (Selected) | C38: =OFFSET(C35,$G$2-1,0)
A40: Terminal Value Multiple - Base | C40: 11
A41: Terminal Value Multiple - Bull | C41: 13
A42: Terminal Value Multiple - Bear | C42: 9
A43: Terminal Value Multiple (Selected) | C43: =OFFSET(C40,$G$2-1,0)

Sheet Financial Statements
A1: Whitecap Resources Inc. (WCP.TO) - Historical Financial Statements
A3: ($ in millions) | C3: FY2022 | D3: FY2023 | E3: FY2024 | F3: FY2025
A5: Income Statement
A6: Total Revenue | C6: 4780.4 | D6: 3848.9 | E6: 3937.9 | F6: 5908.8
A7: Cost of Revenue | C7: 1668.3 | D7: 1484.1 | E7: 1575.3 | F7: 2448.4
A8: Gross Profit | C8: 3112.1 | D8: 2364.8 | E8: 2362.6 | F8: 3460.4
A9: Gross Margin | C9: 0.65101247 | D9: 0.61440931 | E9: 0.59996445 | F9: 0.58563499
A11: R&D Expense | C11: 0 | D11: 0 | E11: 0 | F11: 0
A12: SG&A Expense | C12: 397.3 | D12: 370.9 | E12: 361.7 | F12: 423.5
A13: Operating Income (EBIT) | C13: 1791.1 | D13: 1024.5 | E13: 937.3 | F13: 1176.6
A14: EBIT Margin | C14: 0.37467576 | D14: 0.26617995 | E14: 0.23802026 | F14: 0.19912673
A16: Interest Expense | C16: 62.9 | D16: 88.6 | E16: 89.7 | F16: 141.3
A17: Tax Provision | C17: 548.5 | D17: 281.7 | E17: 263 | F17: 341
A18: Net Income | C18: 1676.1 | D18: 889 | E18: 812.3 | F18: 984.6
A19: Net Margin | C19: 0.3506192 | D19: 0.23097508 | E19: 0.20627746 | F19: 0.16663282
... A24: D&A | C24: 806.5 | D24: 865.2 | E24: 975.2 | F24: 1709.3
A27: Balance Sheet
A28: Cash & Equivalents | C28: 0 | D28: 0 | E28: 362.3 | F28: 59.4
A29: Current Assets | C29: 972.4 | D29: 511.5 | E29: 884.3 | F29: 1184.1
A30: Net PP&E | C30: 8545.3 | D30: 8964.5 | E30: 8972.1 | F30: 18001.9
A31: Goodwill | C31: 0 | D31: 0 | E31: 0 | F31: 0
A32: Total Assets | C32: 9529.8 | D32: 9602.2 | E32: 9950.1 | F32: 19294.7
A34: Current Liabilities | C34: 754.2 | D34: 567.6 | E34: 836.4 | F34: 1687.6
A35: Total Debt | C35: 1873.6 | D35: 1382.7 | E35: 1143.1 | F35: 3767.2
A36: Total Liabilities | C36: 4480.1 | D36: 4125.2 | E36: 4202.8 | F36: 8292.5
A38: Total Equity | C38: 5049.7 | D38: 5477 | E38: 5747.3 | F38: 11002.2
A41: Cash Flow Statement
A42: Operating Cash Flow | C42: 2183.1 | D42: 1742.5 | E42: 1833.5 | F42: 2685.9
A43: Capital Expenditure | C43: -694.5 | D43: -1124.9 | E43: -1136.7 | F43: -2076.5
A44: Free Cash Flow | C44: 1488.6 | D44: 617.6 | E44: 696.8 | F44: 609.4
A46: D&A | C46: 8.7 | D46: 9.3 | E46: 12 | F46: 0
A47: Stock-Based Compensation | C47: 11.1 | D47: 14.4 | E47: 16.6 | F47: 22.2
A48: Change in Working Capital | C48: -139.7 | D48: -48.9 | E48: 201.3 | F48: -251.9

Sheet Model
A1: Whitecap Resources Inc. (WCP.TO) - Financial Model
A2: Scenario: | C2: =Assumptions!G2
A4: ($M) | C4: FY2022 | D4: FY2023 | E4: FY2024 | F4: FY2025 | G4: FY2026 | H4: FY2027 | I4: FY2028 | J4: FY2029 | K4: FY2030
G5: Proj. | H5: Proj. | I5: Proj. | J5: Proj. | K5: Proj.
A7: Revenue by Segment
A8: Oil & Gas E&P | C8: 4780.4 | D8: 3848.9 | E8: 3937.9 | F8: 5908.8 | G8: =Assumptions!G12 | H8: =Assumptions!H12 | I8: =Assumptions!I12 | J8: =Assumptions!J12 | K8: =Assumptions!K12
A9: YoY Growth | D9: =IFERROR(D8/C8-1,"-") | E9: =IFERROR(E8/D8-1,"-") | F9: =IFERROR(F8/E8-1,"-") | G9: =IFERROR(G8/F8-1,"-") | H9: =IFERROR(H8/G8-1,"-") | I9: =IFERROR(I8/H8-1,"-") | J9: =IFERROR(J8/I8-1,"-") | K9: =IFERROR(K8/J8-1,"-")
A11: Total Revenue | C11: =C8 | D11: =D8 | E11: =E8 | F11: =F8 | G11: =G8 | H11: =H8 | I11: =I8 | J11: =J8 | K11: =K8
A12: Revenue Growth % | D12: =IFERROR(D11/C11-1,"-") | E12: =IFERROR(E11/D11-1,"-") | F12: =IFERROR(F11/E11-1,"-") | G12: =IFERROR(G11/F11-1,"-") | H12: =IFERROR(H11/G11-1,"-") | I12: =IFERROR(I11/H11-1,"-") | J12: =IFERROR(J11/I11-1,"-") | K12: =IFERROR(K11/J11-1,"-")
A14: Profit & Loss
A15: Revenue | C15: =C11 | D15: =D11 | E15: =E11 | F15: =F11 | G15: =G11 | H15: =H11 | I15: =I11 | J15: =J11 | K15: =K11
A16: Cost of Goods Sold (COGS) | C16: 1668.3 | D16: 1484.1 | E16: 1575.3 | F16: 2448.4 | G16: =-G15*(1-Assumptions!G18) | H16: =-H15*(1-Assumptions!H18) | I16: =-I15*(1-Assumptions!I18) | J16: =-J15*(1-Assumptions!J18) | K16: =-K15*(1-Assumptions!K18)
A17: Gross Profit | C17: =C15+C16 | D17: =D15+D16 | E17: =E15+E16 | F17: =F15+F16 | G17: =G15+G16 | H17: =H15+H16 | I17: =I15+I16 | J17: =J15+J16 | K17: =K15+K16
A18: Gross Margin % | C18: =IFERROR(C17/C15,"-") | D18: =IFERROR(D17/D15,"-") | E18: =IFERROR(E17/E15,"-") | F18: =IFERROR(F17/F15,"-") | G18: =IFERROR(G17/G15,"-") | H18: =IFERROR(H17/H15,"-") | I18: =IFERROR(I17/I15,"-") | J18: =IFERROR(J17/J15,"-") | K18: =IFERROR(K17/K15,"-")
A20: SG&A Expense | C20: 397.3 | D20: 370.9 | E20: 361.7 | F20: 423.5 | G20: =-G15*Assumptions!G24 | H20: =-H15*Assumptions!H24 | I20: =-I15*Assumptions!I24 | J20: =-J15*Assumptions!J24 | K20: =-K15*Assumptions!K24
A21: R&D Expense | C21: 0 | D21: 0 | E21: 0 | F21: 0 | G21: =-G15*Assumptions!G30 | H21: =-H15*Assumptions!H30 | I21: =-I15*Assumptions!I30 | J21: =-J15*Assumptions!J30 | K21: =-K15*Assumptions!K30
A22: Depreciation & Amortization | C22: 806.5 | D22: 865.2 | E22: 975.2 | F22: 1709.3 | G22: =-G15*Assumptions!G32 | H22: =-H15*Assumptions!H32 | I22: =-I15*Assumptions!I32 | J22: =-J15*Assumptions!J32 | K22: =-K15*Assumptions!K32
A24: EBITDA | C24: =C17+C20+C21 | D24: =D17+D20+D21 | E24: =E17+E20+E21 | F24: =F17+F20+F21 | G24: =G17+G20+G21 | H24: =H17+H20+H21 | I24: =I17+I20+I21 | J24: =J17+J20+J21 | K24: =K17+K20+K21
A25: EBITDA Margin % | C25: =IFERROR(C24/C15,"-") | D25: =IFERROR(D24/D15,"-") | E25: =IFERROR(E24/E15,"-") | F25: =IFERROR(F24/F15,"-") | G25: =IFERROR(G24/G15,"-") | H25: =IFERROR(H24/H15,"-") | I25: =IFERROR(I24/I15,"-") | J25: =IFERROR(J24/J15,"-") | K25: =IFERROR(K24/K15,"-")
A26: EBIT | C26: =C24+C22 | D26: =D24+D22 | E26: =E24+E22 | F26: =F24+F22 | G26: =G24+G22 | H26: =H24+H22 | I26: =I24+I22 | J26: =J24+J22 | K26: =K24+K22
A27: EBIT Margin % | C27: =IFERROR(C26/C15,"-") | D27: =IFERROR(D26/D15,"-") | E27: =IFERROR(E26/E15,"-") | F27: =IFERROR(F26/F15,"-") | G27: =IFERROR(G26/G15,"-") | H27: =IFERROR(H26/H15,"-") | I27: =IFERROR(I26/I15,"-") | J27: =IFERROR(J26/J15,"-") | K27: =IFERROR(K26/K15,"-")
A29: Interest Expense | C29: 62.9 | D29: 88.6 | E29: 89.7 | F29: 141.3 | G29: 141.3 | H29: 141.3 | I29: 141.3 | J29: 141.3 | K29: 141.3
A30: Earnings Before Tax (EBT) | C30: =C26+C29 | D30: =D26+D29 | E30: =E26+E29 | F30: =F26+F29 | G30: =G26+G29 | H30: =H26+H29 | I30: =I26+I29 | J30: =J26+J29 | K30: =K26+K29
A31: Taxes | C31: 548.5 | D31: 281.7 | E31: 263 | F31: 341 | G31: =-ABS(G30)*Assumptions!G34 | H31: =-ABS(H30)*Assumptions!H34 | I31: =-ABS(I30)*Assumptions!I34 | J31: =-ABS(J30)*Assumptions!J34 | K31: =-ABS(K30)*Assumptions!K34
A32: Net Income | C32: =C30+C31 | D32: =D30+D31 | E32: =E30+E31 | F32: =F30+F31 | G32: =G30+G31 | H32: =H30+H31 | I32: =I30+I31 | J32: =J30+J31 | K32: =K30+K31
A33: Net Margin % | C33: =IFERROR(C32/C15,"-") | D33: =IFERROR(D32/D15,"-") | E33: =IFERROR(E32/E15,"-") | F33: =IFERROR(F32/F15,"-") | G33: =IFERROR(G32/G15,"-") | H33: =IFERROR(H32/H15,"-") | I33: =IFERROR(I32/I15,"-") | J33: =IFERROR(J32/J15,"-") | K33: =IFERROR(K32/K15,"-")
A36: Cash Flow
A37: EBITDA | C37: =C24 | D37: =D24 | E37: =E24 | F37: =F24 | G37: =G24 | H37: =H24 | I37: =I24 | J37: =J24 | K37: =K24
A38: (-) Taxes | C38: =C31 | D38: =D31 | E38: =E31 | F38: =F31 | G38: =G31 | H38: =H31 | I38: =I31 | J38: =J31 | K38: =K31
A39: (+/-) Change in Working Capital | C39: -139.7 | D39: -48.9 | E39: 201.3 | F39: -251.9 | G39: 0 | H39: 0 | I39: 0 | J39: 0 | K39: 0
A40: Operating Cash Flow | C40: =C37+C38+C39 | D40: =D37+D38+D39 | E40: =E37+E38+E39 | F40: =F37+F38+F39 | G40: =G37+G38+G39 | H40: =H37+H38+H39 | I40: =I37+I38+I39 | J40: =J37+J38+J39 | K40: =K37+K38+K39
A42: (-) Capital Expenditure | C42: -694.5 | D42: -1124.9 | E42: -1136.7 | F42: -2076.5 | G42: =-ABS(G15)*Assumptions!G33 | H42: =-ABS(H15)*Assumptions!H33 | I42: =-ABS(I15)*Assumptions!I33 | J42: =-ABS(J15)*Assumptions!J33 | K42: =-ABS(K15)*Assumptions!K33
A43: Unlevered Free Cash Flow (UFCF) | C43: =C40+C42 | D43: =D40+D42 | E43: =E40+E42 | F43: =F40+F42 | G43: =G40+G42 | H43: =H40+H42 | I43: =I40+I42 | J43: =J40+J42 | K43: =K40+K42
A200: __REF_EBITDA_ROW | B200: 24
A201: __REF_TAXES_ROW | B201: 31
A202: __REF_CAPEX_ROW | B202: 42
A203: __REF_UFCF_ROW | B203: 43
A204: __REF_WC_ROW | B204: 39
A205: __REF_NI_ROW | B205: 32
A206: __REF_TOTAL_REV_ROW | B206: 11

Sheet Valuation
A1: Whitecap Resources Inc. (WCP.TO) - DCF Valuation
A2: Scenario: | C2: =Assumptions!G2 | E2: Current Price: | F2: 15.54
A4: Year | G4: 2026 | H4: 2027 | I4: 2028 | J4: 2029 | K4: 2030
A5: Year # | G5: 1 | H5: 2 | I5: 3 | J5: 4 | K5: 5
A7: DCF Inputs (from Model)
A8: EBITDA ($M) | G8: =INDIRECT("Model!"&"G"&Model!B200) | H8: =INDIRECT("Model!"&"H"&Model!B200) | I8: =INDIRECT("Model!"&"I"&Model!B200) | J8: =INDIRECT("Model!"&"J"&Model!B200) | K8: =INDIRECT("Model!"&"K"&Model!B200)
A9: (-) Taxes ($M) | G9: =INDIRECT("Model!"&"G"&Model!B201) | H9: =INDIRECT("Model!"&"H"&Model!B201) | I9: =INDIRECT("Model!"&"I"&Model!B201) | J9: =INDIRECT("Model!"&"J"&Model!B201) | K9: =INDIRECT("Model!"&"K"&Model!B201)
A10: (+/-) Change in WC ($M) | G10: =INDIRECT("Model!"&"G"&Model!B204) | H10: =INDIRECT("Model!"&"H"&Model!B204) | I10: =INDIRECT("Model!"&"I"&Model!B204) | J10: =INDIRECT("Model!"&"J"&Model!B204) | K10: =INDIRECT("Model!"&"K"&Model!B204)
A11: (-) CapEx ($M) | G11: =INDIRECT("Model!"&"G"&Model!B202) | H11: =INDIRECT("Model!"&"H"&Model!B202) | I11: =INDIRECT("Model!"&"I"&Model!B202) | J11: =INDIRECT("Model!"&"J"&Model!B202) | K11: =INDIRECT("Model!"&"K"&Model!B202)
A12: Unlevered Free Cash Flow ($M) | G12: =G8+G9+G10+G11 | H12: =H8+H9+H10+H11 | I12: =I8+I9+I10+I11 | J12: =J8+J9+J10+J11 | K12: =K8+K9+K10+K11
A14: Discounted Cash Flow
A15: WACC | C15: =Assumptions!C42
A16: Terminal Value Multiple | C16: =Assumptions!C48
A18: Discount Factor | G18: =1/(1+$C$15)^1 | H18: =1/(1+$C$15)^2 | I18: =1/(1+$C$15)^3 | J18: =1/(1+$C$15)^4 | K18: =1/(1+$C$15)^5
A19: PV of UFCF ($M) | G19: =G12*G18 | H19: =H12*H18 | I19: =I12*I18 | J19: =J12*J18 | K19: =K12*K18
A21: Terminal Value ($M) | K21: =K8*$C$16
A22: PV of Terminal Value ($M) | K22: =K21*K18
A24: Valuation Summary
A25: Sum of PV of UFCF ($M) | C25: =SUM(G19:K19)
A26: PV of Terminal Value ($M) | C26: =K22
A27: Enterprise Value ($M) | C27: =C25+C26
A29: (-) Net Debt ($M) | C29: -3707.8
A30: Equity Value ($M) | C30: =C27+C29
A32: Shares Outstanding (M) | C32: 1213.8
A33: Equity Value per Share ($) | C33: =C30/C32
A34: Upside / Downside vs Current | C34: =C33/15.54-1
A37: Sensitivity Analysis: WACC vs Terminal Value Multiple
A38: WACC \ TV Multiple | C38: 7x | D38: 9x | E38: 11x | F38: 13x | G38: 15x
A39: 0.0499 | C39: =(G$12/(1+$A$39)^1+H$12/(1+$A$39)^2+I$12/(1+$A$39)^3+J$12/(1+$A$39)^4+K$12/(1+$A$39)^5+K$8*7/(1+$A$39)^5+$C$29)/$C$32 | D39: =(G$12/(1+$A$39)^1+H$12/(1+$A$39)^2+I$12/(1+$A$39)^3+J$12/(1+$A$39)^4+K$12/(1+$A$39)^5+K$8*9/(1+$A$39)^5+$C$29)/$C$32 | E39: =(G$12/(1+$A$39)^1+H$12/(1+$A$39)^2+I$12/(1+$A$39)^3+J$12/(1+$A$39)^4+K$12/(1+$A$39)^5+K$8*11/(1+$A$39)^5+$C$29)/$C$32 | F39: =(G$12/(1+$A$39)^1+H$12/(1+$A$39)^2+I$12/(1+$A$39)^3+J$12/(1+$A$39)^4+K$12/(1+$A$39)^5+K$8*13/(1+$A$39)^5+$C$29)/$C$32 | G39: =(G$12/(1+$A$39)^1+H$12/(1+$A$39)^2+I$12/(1+$A$39)^3+J$12/(1+$A$39)^4+K$12/(1+$A$39)^5+K$8*15/(1+$A$39)^5+$C$29)/$C$32
A40: 0.0599 | C40: =(G$12/(1+$A$40)^1+H$12/(1+$A$40)^2+I$12/(1+$A$40)^3+J$12/(1+$A$40)^4+K$12/(1+$A$40)^5+K$8*7/(1+$A$40)^5+$C$29)/$C$32 | D40: =(G$12/(1+$A$40)^1+H$12/(1+$A$40)^2+I$12/(1+$A$40)^3+J$12/(1+$A$40)^4+K$12/(1+$A$40)^5+K$8*9/(1+$A$40)^5+$C$29)/$C$32 | E40: =(G$12/(1+$A$40)^1+H$12/(1+$A$40)^2+I$12/(1+$A$40)^3+J$12/(1+$A$40)^4+K$12/(1+$A$40)^5+K$8*11/(1+$A$40)^5+$C$29)/$C$32 | F40: =(G$12/(1+$A$40)^1+H$12/(1+$A$40)^2+I$12/(1+$A$40)^3+J$12/(1+$A$40)^4+K$12/(1+$A$40)^5+K$8*13/(1+$A$40)^5+$C$29)/$C$32 | G40: =(G$12/(1+$A$40)^1+H$12/(1+$A$40)^2+I$12/(1+$A$40)^3+J$12/(1+$A$40)^4+K$12/(1+$A$40)^5+K$8*15/(1+$A$40)^5+$C$29)/$C$32
A41: 0.0699 | C41: =(G$12/(1+$A$41)^1+H$12/(1+$A$41)^2+I$12/(1+$A$41)^3+J$12/(1+$A$41)^4+K$12/(1+$A$41)^5+K$8*7/(1+$A$41)^5+$C$29)/$C$32 | D41: =(G$12/(1+$A$41)^1+H$12/(1+$A$41)^2+I$12/(1+$A$41)^3+J$12/(1+$A$41)^4+K$12/(1+$A$41)^5+K$8*9/(1+$A$41)^5+$C$29)/$C$32 | E41: =(G$12/(1+$A$41)^1+H$12/(1+$A$41)^2+I$12/(1+$A$41)^3+J$12/(1+$A$41)^4+K$12/(1+$A$41)^5+K$8*11/(1+$A$41)^5+$C$29)/$C$32 | F41: =(G$12/(1+$A$41)^1+H$12/(1+$A$41)^2+I$12/(1+$A$41)^3+J$12/(1+$A$41)^4+K$12/(1+$A$41)^5+K$8*13/(1+$A$41)^5+$C$29)/$C$32 | G41: =(G$12/(1+$A$41)^1+H$12/(1+$A$41)^2+I$12/(1+$A$41)^3+J$12/(1+$A$41)^4+K$12/(1+$A$41)^5+K$8*15/(1+$A$41)^5+$C$29)/$C$32
A42: 0.0799 | C42: =(G$12/(1+$A$42)^1+H$12/(1+$A$42)^2+I$12/(1+$A$42)^3+J$12/(1+$A$42)^4+K$12/(1+$A$42)^5+K$8*7/(1+$A$42)^5+$C$29)/$C$32 | D42: =(G$12/(1+$A$42)^1+H$12/(1+$A$42)^2+I$12/(1+$A$42)^3+J$12/(1+$A$42)^4+K$12/(1+$A$42)^5+K$8*9/(1+$A$42)^5+$C$29)/$C$32 | E42: =(G$12/(1+$A$42)^1+H$12/(1+$A$42)^2+I$12/(1+$A$42)^3+J$12/(1+$A$42)^4+K$12/(1+$A$42)^5+K$8*11/(1+$A$42)^5+$C$29)/$C$32 | F42: =(G$12/(1+$A$42)^1+H$12/(1+$A$42)^2+I$12/(1+$A$42)^3+J$12/(1+$A$42)^4+K$12/(1+$A$42)^5+K$8*13/(1+$A$42)^5+$C$29)/$C$32 | G42: =(G$12/(1+$A$42)^1+H$12/(1+$A$42)^2+I$12/(1+$A$42)^3+J$12/(1+$A$42)^4+K$12/(1+$A$42)^5+K$8*15/(1+$A$42)^5+$C$29)/$C$32
A43: 0.0899 | C43: =(G$12/(1+$A$43)^1+H$12/(1+$A$43)^2+I$12/(1+$A$43)^3+J$12/(1+$A$43)^4+K$12/(1+$A$43)^5+K$8*7/(1+$A$43)^5+$C$29)/$C$32 | D43: =(G$12/(1+$A$43)^1+H$12/(1+$A$43)^2+I$12/(1+$A$43)^3+J$12/(1+$A$43)^4+K$12/(1+$A$43)^5+K$8*9/(1+$A$43)^5+$C$29)/$C$32 | E43: =(G$12/(1+$A$43)^1+H$12/(1+$A$43)^2+I$12/(1+$A$43)^3+J$12/(1+$A$43)^4+K$12/(1+$A$43)^5+K$8*11/(1+$A$43)^5+$C$29)/$C$32 | F43: =(G$12/(1+$A$43)^1+H$12/(1+$A$43)^2+I$12/(1+$A$43)^3+J$12/(1+$A$43)^4+K$12/(1+$A$43)^5+K$8*13/(1+$A$43)^5+$C$29)/$C$32 | G43: =(G$12/(1+$A$43)^1+H$12/(1+$A$43)^2+I$12/(1+$A$43)^3+J$12/(1+$A$43)^4+K$12/(1+$A$43)^5+K$8*15/(1+$A$43)^5+$C$29)/$C$32
A44: 0.0999 | C44: =(G$12/(1+$A$44)^1+H$12/(1+$A$44)^2+I$12/(1+$A$44)^3+J$12/(1+$A$44)^4+K$12/(1+$A$44)^5+K$8*7/(1+$A$44)^5+$C$29)/$C$32 | D44: =(G$12/(1+$A$44)^1+H$12/(1+$A$44)^2+I$12/(1+$A$44)^3+J$12/(1+$A$44)^4+K$12/(1+$A$44)^5+K$8*9/(1+$A$44)^5+$C$29)/$C$32 | E44: =(G$12/(1+$A$44)^1+H$12/(1+$A$44)^2+I$12/(1+$A$44)^3+J$12/(1+$A$44)^4+K$12/(1+$A$44)^5+K$8*11/(1+$A$44)^5+$C$29)/$C$32 | F44: =(G$12/(1+$A$44)^1+H$12/(1+$A$44)^2+I$12/(1+$A$44)^3+J$12/(1+$A$44)^4+K$12/(1+$A$44)^5+K$8*13/(1+$A$44)^5+$C$29)/$C$32 | G44: =(G$12/(1+$A$44)^1+H$12/(1+$A$44)^2+I$12/(1+$A$44)^3+J$12/(1+$A$44)^4+K$12/(1+$A$44)^5+K$8*15/(1+$A$44)^5+$C$29)/$C$32
A45: 0.1099 | C45: =(G$12/(1+$A$45)^1+H$12/(1+$A$45)^2+I$12/(1+$A$45)^3+J$12/(1+$A$45)^4+K$12/(1+$A$45)^5+K$8*7/(1+$A$45)^5+$C$29)/$C$32 | D45: =(G$12/(1+$A$45)^1+H$12/(1+$A$45)^2+I$12/(1+$A$45)^3+J$12/(1+$A$45)^4+K$12/(1+$A$45)^5+K$8*9/(1+$A$45)^5+$C$29)/$C$32 | E45: =(G$12/(1+$A$45)^1+H$12/(1+$A$45)^2+I$12/(1+$A$45)^3+J$12/(1+$A$45)^4+K$12/(1+$A$45)^5+K$8*11/(1+$A$45)^5+$C$29)/$C$32 | F45: =(G$12/(1+$A$45)^1+H$12/(1+$A$45)^2+I$12/(1+$A$45)^3+J$12/(1+$A$45)^4+K$12/(1+$A$45)^5+K$8*13/(1+$A$45)^5+$C$29)/$C$32 | G45: =(G$12/(1+$A$45)^1+H$12/(1+$A$45)^2+I$12/(1+$A$45)^3+J$12/(1+$A$45)^4+K$12/(1+$A$45)^5+K$8*15/(1+$A$45)^5+$C$29)/$C$32
